{
  "id": "cy-law-2009-1-10",
  "type": "statute",
  "title": "Ο περί Χημικών Ουσιών, Παρασκευασμάτων και Προϊόντων Νόμος του 2009 (10(I)/2009)",
  "short_name": "Ν. 2009/1/10",
  "status": "in_force",
  "url": "https://www.cylaw.org/nomoi/enop/non-ind/2009_1_10/full.html",
  "provisions": [
    {
      "provision_ref": "sec1",
      "chapter": "ΜΕΡΟΣ Ι ΓΕΝΙΚΕΣ ΔΙΑΤΑΞΕΙΣ",
      "section": "1",
      "title": "Άρθρο 1: Συνοπτικός τίτλος",
      "content": "1. Ο παρών Νόμος θα αναφέρεται ως ο περί Χημικών Ουσιών, Παρασκευασμάτων και Προϊόντων Νόμος του 2009."
    },
    {
      "provision_ref": "sec2",
      "chapter": "ΜΕΡΟΣ Ι ΓΕΝΙΚΕΣ ΔΙΑΤΑΞΕΙΣ",
      "section": "2",
      "title": "Άρθρο 2: Ερμηνεία",
      "content": "2.-(1) Στον παρόντα Νόμο, εκτός αν από το κείμενο προκύπτει διαφορετική έννοια -\n«αεροσκάφος» έχει την έννοια που αποδίδει στον όρο αυτό το άρθρο 2 του περί Πολιτικής Αεροπορίας Νόμου.\n«αστυνομικός» έχει την έννοια που αποδίδει στον όρο αυτό το εδάφιο (1) του άρθρου 2 του περί Αστυνομίας Νόμου·\n«δικαστήριο» σημαίνει Επαρχιακό Δικαστήριο αρμόδιας δικαιοδοσίας·\n«επικίνδυνες ουσίες και/ ή παρασκευάσματα» σημαίνει τις ουσίες και/ ή τα παρασκευάσματα, που εμπίπτουν σε μία ή περισσότερες από τις ακόλουθες κατηγορίες, όπως αυτές ορίζονται στο εδάφιο (2)·\n(α) εκρηκτικές·\n(β) οξειδωτικές·\n(γ) εξαιρετικά εύφλεκτες·\n(δ) πολύ εύφλεκτες·\n(ε) εύφλεκτες·\n(στ) πολύ τοξικές·\n(ζ) τοξικές·\n(η) επιβλαβείς·\n(θ) διαβρωτικές·\n(ι) ερεθιστικές·\n(ια) ευαισθητοποιητικές·\n(ιβ) καρκινογόνες·\n(ιγ) μεταλλαξιογόνες·\n(ιδ) τοξικές για την αναπαραγωγή· και\n(ιε) επικίνδυνες για το περιβάλλον·\n«κανονισμός REACH» σημαίνει τον κανονισμό (ΕΚ) αριθ. 1907/2006 του Ευρωπαϊκού Κοινοβουλίου και του Συμβουλίου της 18ης Δεκεμβρίου 2006 για την καταχώριση, την αξιολόγηση, την αδειοδότηση και τους περιορισμούς των χημικών προϊόντων (REACH) και για την ίδρυση του Eυρωπαϊκού Oργανισμού Χημικών Προϊόντων καθώς και για την τροποποίηση της οδηγίας 1999/45/ΕΚ και για την κατάργηση του κανονισμού (ΕΟΚ) αριθ. 793/93 του Συμβουλίου και του κανονισμού (ΕΚ) αριθ. 1488/94 της Επιτροπής καθώς και της οδηγίας 76/769/ΕΟΚ του Συμβουλίου και των οδηγιών της Επιτροπής 91/155/ΕΟΚ, 93/67/ΕΟΚ, 93/105/ΕΚ και 2000/21/ΕΚ, όπως εκάστοτε τροποποιείται ή αντικαθίσταται·\n«κανονισμός ΕΚ/340/2008» σημαίνει τον κανονισμό (ΕΚ) αριθ. 340/2008 της Επιτροπής της 16ης Απριλίου 2008 σχετικά με τα τέλη και τις επιβαρύνσεις που πρέπει να καταβάλλονται στον Ευρωπαϊκό Οργανισμό Χημικών Προϊόντων σύμφωνα με τον κανονισμό (ΕΚ) αριθ. 1907/2006 του Ευρωπαϊκού Κοινοβουλίου και του Συμβουλίου για την καταχώριση, την αξιολόγηση, την αδειοδότηση και τους περιορισμούς των χημικών προϊόντων (REACH), όπως εκάστοτε τροποποιείται ή αντικαθίσταται·\n«κανονισμός ΕΚ/440/2008» σημαίνει τον κανονισμό (ΕΚ) αριθ. 440/2008 της Επιτροπής της 30ης Μαΐου 2008, για καθορισμό των μεθόδων δοκιμής κατ’ εφαρμογήν του κανονισμού (ΕΚ) αριθ. 1907/2006 του Ευρωπαϊκού Κοινοβουλίου και του Συμβουλίου, για την καταχώριση, την αξιολόγηση, την αδειοδότηση και τους περιορισμούς των χημικών προϊόντων (REACH), όπως εκάστοτε τροποποιείται ή αντικαθίσταται·\n«κανονισμός ΕΚ/689/2008» σημαίνει τον κανονισμό (ΕΚ) αριθ. 689/2008 του Ευρωπαϊκού Κοινοβουλίου και του Συμβουλίου της 17ης Ιουνίου 2008 σχετικά με τις εξαγωγές και εισαγωγές επικίνδυνων χημικών προϊόντων, όπως εκάστοτε τροποποιείται ή αντικαθίσταται·\n«όχημα» έχει την έννοια που αποδίδει στον όρο αυτό το άρθρο 2 του περί Έγκρισης Τύπου Οχημάτων Νόμου·\n«πλοίο» έχει την έννοια που αποδίδει στον όρο αυτό το άρθρο 2 του περί Εμπορικής Ναυτιλίας (Κοινοτικό Σύστημα Παρακολούθησης και Ενημέρωσης Σχετικά με την Κυκλοφορία Πλοίων) Νόμου·\n«σκάφος» περιλαμβάνει αεροσκάφος και πλοίο·\n«υποστατικό» περιλαμβάνει -\n(i) οποιαδήποτε επίγεια ή υπόγεια ή υπεράκτια εγκατάσταση και οποιαδήποτε άλλη εγκατάσταση είτε επιπλέουσα είτε ευρισκόμενη στο βυθό της θάλασσας ή λίμνης είτε ευρισκόμενη σε έδαφος που καλύπτεται από νερό·\n(ii) οποιαδήποτε σκηνή ή κινητή κατασκευή·\n(iii) οποιοδήποτε όχημα ή σκάφος· και\n(iv) οποιοδήποτε κατασκευαστικό έργο, οικοδομή, έργο διαχωρισμού γης, έργο οδοποιίας, οδογέφυρα, γέφυρα, σήραγγα, αποχετευτικό και αποστραγγιστικό έργο, έργο ύδρευσης ή άρδευσης, υπόγεια κατασκευή, δεξαμενή, υπόγειο ή υπέργειο δίκτυο υπηρεσιών, υπόγειο ή υπέργειο αγωγό, υδραγωγείο ή οποιοδήποτε άλλο τεχνικό έργο· και\n«Υπουργός» σημαίνει τον Υπουργό Εργασίας και Κοινωνικών Ασφαλίσεων.\n(2) Αναφορικά με επικίνδυνες ουσίες και/ ή παρασκευάσματα, για σκοπούς ταξινόμησης -\n(α) «εκρηκτικές» σημαίνει τις στερεές, υγρές, παχύρρευστες ή ζελατινώδεις ουσίες και/ ή παρασκευάσματα, που μπορούν να αντιδράσουν εξώθερμα, με ταυτόχρονη ταχεία έκλυση αερίων, ακόμη και χωρίς την παρουσία ατμοσφαιρικού οξυγόνου και που, υπό καθορισμένες συνθήκες δοκιμής, εκπυρσοκροτούν, αναφλέγονται έντονα και γρήγορα ή εκρήγνυνται υπό την επίδραση θερμότητας και περιορισμού·\n(β) «οξειδωτικές» σημαίνει τις ουσίες και/ ή παρασκευάσματα, τα οποία, όταν έρχονται σε επαφή με άλλες ουσίες και ιδίως εύφλεκτες ουσίες, προκαλούν ισχυρώς εξώθερμη αντίδραση·\n(γ) «εξαιρετικά εύφλεκτες» σημαίνει τις ουσίες και/ ή παρασκευάσματα με εξαιρετικά χαμηλό σημείο ανάφλεξης και χαμηλό σημείο ζέσεως, καθώς και αέριες ουσίες και παρασκευάσματα, τα οποία, υπό κανονική θερμοκρασία και πίεση, αναφλέγονται στον αέρα·\n(δ) «πολύ εύφλεκτες» σημαίνει τις ουσίες και/ ή παρασκευάσματα, τα οποία -\n(i) μπορεί να θερμανθούν και τελικά να αναφλεγούν στον αέρα, σε συνήθη θερμοκρασία, χωρίς έξωθεν παροχή ενέργειας, ή\n(ii) σε στερεά κατάσταση, μπορούν να αναφλεγούν εύκολα μετά από σύντομη επίδραση πηγής ανάφλεξης και οι οποίες εξακολουθούν να φλέγονται ή να καίγονται μετά την απόσυρση της πηγής ανάφλεξης, ή\n(iii) σε υγρή κατάσταση, με πολύ χαμηλό σημείο ανάφλεξης, ή σε επαφή με το νερό ή με αέρα υψηλής υγρασίας, εκλύουν εξαιρετικά εύφλεκτα αέρια σε επικίνδυνες ποσότητες·\n(ε) «εύφλεκτες» σημαίνει τις υγρές ουσίες και/ ή παρασκευάσματα με πολύ χαμηλό σημείο ανάφλεξης·\n(στ) «πολύ τοξικές» σημαίνει τις ουσίες και/ ή τα παρασκευάσματα, οι οποίες, εισερχόμενες στον ανθρώπινο οργανισμό με εισπνοή, κατάποση ή απορρόφηση μέσω του δέρματος ή με οποιοδήποτε άλλο τρόπο, ακόμη και σε ελάχιστη ποσότητα, προκαλούν το θάνατο ή οξείες ή χρόνιες βλάβες της υγείας·\n(ζ) «τοξικές» σημαίνει τις ουσίες και/ ή τα παρασκευάσματα, οι οποίες, εισερχόμενες στον ανθρώπινο οργανισμό με εισπνοή, κατάποση ή απορρόφηση μέσω του δέρματος ή με οποιοδήποτε άλλο τρόπο, ακόμα και σε μικρές ποσότητες, προκαλούν το θάνατο ή οξείες ή χρόνιες βλάβες της υγείας·\n(η) «επιβλαβείς» σημαίνει τις ουσίες και/ ή τα παρασκευάσματα, οι οποίες, εισερχόμενες στον ανθρώπινο οργανισμό με εισπνοή, κατάποση ή απορρόφηση μέσω του δέρματος ή με οποιοδήποτε άλλο τρόπο, μπορούν να προκαλέσουν το θάνατο ή οξείες ή χρόνιες βλάβες της υγείας·\n(θ) «διαβρωτικές» σημαίνει τις ουσίες και/ ή τα παρασκευάσματα, οι οποίες, σε επαφή με ζώντες ιστούς, μπορούν να τους καταστρέψουν·\n(ι) «ερεθιστικές» σημαίνει τις μη διαβρωτικές ουσίες και/ ή τα παρασκευάσματα, οι οποίες, με άμεση, παρατεταμένη ή επαναλαμβανόμενη επαφή με το δέρμα ή τους βλεννογόνους, μπορούν να προκαλέσουν φλεγμονές·\n(ια) «ευαισθητοποιητικές» σημαίνει τις ουσίες και/ ή τα παρασκευάσματα, οι οποίες, εισερχόμενες στον ανθρώπινο οργανισμό με εισπνοή, κατάποση ή απορρόφηση μέσω του δέρματος ή με οποιοδήποτε άλλο τρόπο, μπορούν να προκαλέσουν τέτοια αντίδραση του οργανισμού (υπερευαισθητοποίηση) ώστε, με περαιτέρω έκθεση σε αυτή την ουσία ή το παρασκεύασμα, να προκαλούνται χαρακτηριστικές επιβλαβείς αντιδράσεις·\n(ιβ) «καρκινογόνες» σημαίνει τις ουσίες και/ ή τα παρασκευάσματα, οι οποίες, εισερχόμενες στον ανθρώπινο οργανισμό με εισπνοή, κατάποση ή απορρόφηση μέσω του δέρματος ή με οποιοδήποτε άλλο τρόπο, μπορούν να προκαλέσουν καρκίνο ή να αυξήσουν τη συχνότητά του·\n(ιγ) «μεταλλαξιογόνες» σημαίνει τις ουσίες και/ ή τα παρασκευάσματα, οι οποίες, εισερχόμενες στον ανθρώπινο οργανισμό με εισπνοή, κατάποση ή απορρόφηση μέσω του δέρματος ή με οποιοδήποτε άλλο τρόπο, μπορούν να προκαλέσουν κληρονομικά γενετικά ελαττώματα ή να αυξήσουν τη συχνότητά τους·\n(ιδ) «τοξικές για την αναπαραγωγή» σημαίνει τις ουσίες και/ ή τα παρασκευάσματα, οι οποίες, εισερχόμενες στον ανθρώπινο οργανισμό με εισπνοή, κατάποση ή απορρόφηση μέσω του δέρματος ή με οποιοδήποτε άλλο τρόπο, μπορούν να προκαλέσουν ή να αυξήσουν τη συχνότητα μη κληρονομικών επιβλαβών φαινομένων στους απογόνους ή να επιδράσουν δυσμενώς στις αναπαραγωγικές λειτουργίες ή δυνατότητες των δύο φύλων· και\n(ιε) «επικίνδυνες για το περιβάλλον» σημαίνει τις ουσίες και/ ή τα παρασκευάσματα, οι οποίες, αν εισαχθούν στο περιβάλλον, προκαλούν ή μπορεί να προκαλέσουν άμεσο ή μελλοντικό κίνδυνο για ένα ή περισσότερους τομείς του περιβάλλοντος.\n(3) Οποιοιδήποτε άλλοι όροι, οι οποίοι χρησιμοποιούνται στον παρόντα Νόμο και δεν ερμηνεύονται διαφορετικά σε αυτόν, έχουν την έννοια που αποδίδει στους όρους αυτούς ο κανονισμός REACH, ο κανονισμός ΕΚ/689/2008, ο κανονισμός ΕΚ/340/2008 και ο κανονισμός ΕΚ/440/2008, ανάλογα με την περίπτωση."
    },
    {
      "provision_ref": "sec3",
      "chapter": "ΜΕΡΟΣ ΙΙ ΕΚΔΟΣΗ ΚΑΝΟΝΙΣΜΩΝ ΚΑΙ ΔΙΑΤΑΓΜΑΤΩΝ",
      "section": "3",
      "title": "Άρθρο 3: Εξουσία έκδοσης Κανονισμών",
      "content": "3.-(1) To Υπουργικό Συμβούλιο δύναται, ύστερα από εισήγηση του Υπουργού, να εκδίδει Κανονισμούς για τον καθορισμό κάθε θέματος το οποίο χρήζει ή είναι δεκτικό καθορισμού, καθώς και για την καλύτερη εφαρμογή του κανονισμού REACH, του κανονισμού ΕΚ/689/2008, του κανονισμού ΕΚ/340/2008, του κανονισμού ΕΚ/440/2008 και/ ή του παρόντος Νόμου.\n(2) Ειδικότερα και χωρίς επηρεασμό της γενικότητας του εδαφίου (1), οι Κανονισμοί αυτοί μπορούν να προβλέπουν για όλα ή οποιοδήποτε από τα ακόλουθα θέματα:\n(α)την ταξινόμηση, συσκευασία και επισήμανση επικίνδυνων ουσιών και/ ή παρασκευασμάτων·\n(β)την απαγόρευση, τον περιορισμό και/ ή τη ρύθμιση της αποθήκευσης οποιασδήποτε επικίνδυνης ουσίας ή κατηγορίας ή ομάδας επικίνδυνων ουσιών και/ ή παρασκευασμάτων, αναφορικά με τα ακόλουθα:\n(i) την τοποθεσία και το χώρο αποθήκευσης,\n(ii) τα κτίρια και τις εγκαταστάσεις και/ ή τα δοχεία και τα κιβώτια, στα οποία αποθηκεύονται οι ουσίες και/ ή τα παρασκευάσματα,\n(iii) τις φυσικές συνθήκες αποθήκευσης,\n(iv) τις μέγιστες ποσότητες οποιασδήποτε επικίνδυνης ουσίας ή ομάδας ή κατηγορίας επικίνδυνων ουσιών και/ ή παρασκευασμάτων, οι οποίες είναι δυνατό να αποθηκεύονται σε οποιοδήποτε συγκεκριμένο χώρο ή τοποθεσία, και/ ή\n(v) οποιεσδήποτε άλλες ουσίες, οι οποίες δεν πρέπει να αποθηκεύονται μαζί με επικίνδυνες ουσίες και/ ή παρασκευάσματα·\n(γ)τη ρύθμιση και/ ή μεταφορά οποιασδήποτε επικίνδυνης ουσίας ή ομάδας ή κατηγορίας επικίνδυνων ουσιών και/ ή παρασκευασμάτων, περιλαμβανομένων -\n(i) του σχεδιασμού και της κατασκευής, καθώς και των υλικών κατασκευής οποιουδήποτε δοχείου ή κιβωτίου που χρησιμοποιείται για τη μεταφορά οποιασδήποτε επικίνδυνης ουσίας ή ομάδας ή κατηγορίας επικίνδυνων ουσιών και/ ή παρασκευασμάτων,\n(ii) της επισήμανσης και των επιγραφών οποιουδήποτε δοχείου ή κιβωτίου που περιέχει οποιαδήποτε επικίνδυνη ουσία ή ομάδα ή κατηγορία επικίνδυνων ουσιών και/ ή παρασκευασμάτων, και/ ή\n(iii) των προειδοποιήσεων και οδηγιών που πρέπει να αναγράφονται στα δοχεία ή στα κιβώτια καθώς και στα έγγραφα τα οποία τα συνοδεύουν·\n(δ)τον καθορισμό της μέγιστης ποσότητας οποιασδήποτε επικίνδυνης ουσίας ή ομάδας ή κατηγορίας επικίνδυνων ουσιών και/ ή παρασκευασμάτων, που μπορεί να τοποθετηθεί σε οποιοδήποτε δοχείο ή κιβώτιο ή σε οποιοδήποτε όχημα και/ ή σκάφος για μεταφορά·\n(ε)τον καθορισμό οποιασδήποτε ουσίας, με την οποία οι επικίνδυνες ουσίες και/ ή παρασκευάσματα δεν πρέπει να αναμιγνύονται ή να συνυπάρχουν ή οι οποίες δεν πρέπει να μεταφέρονται στο ίδιο δοχείο, κιβώτιο, όχημα και/ ή σκάφος·\n(στ)τον καθορισμό -\n(i) απαιτήσεων ως προς το χειρισμό επικίνδυνων ουσιών ή ομάδας ή κατηγορίας επικίνδυνων ουσιών και/ ή παρασκευασμάτων,\n(ii) προφυ λάξεων που πρέπει να λαμβάνονται, και/ ή\n(iii) ενεργειών που πρέπει να γίνονται,\nσε περίπτωση έκτακτης ανάγκης·\n(ζ)τον περιορισμό της διάθεσης στην αγορά και χρήσης επικίνδυνων ουσιών και/ ή παρασκευασμάτων·\n(η)τον καθορισμό και την εφαρμογή αρχών ορθής εργαστηριακής πρακτικής, αναφορικά με επικίνδυνες ουσίες και/ ή παρασκευάσματα·\n(θ)την εισαγωγή απαίτησης ενημέρωσης και καθοδήγησης των εργοδοτουμένων, αναφορικά με τα θέματα της παραγράφου (ε)·\n(ι)τη θέσπιση ποινικών αδικημάτων για παράβαση των διατάξεων του κανονισμού REACH, του κανονισμού ΕΚ/689/2008 και/ ή των οικείων Κανο νισμών, αναφορικά με τα οποία δύναται να επιβληθούν ποινές που δεν υπερβαίνουν αυτές που προβλέπονται στον παρόντα Νόμο·\n(ια)τον καθορισμό παραβάσεων του κανονισμού REACH, του κανονισμού ΕΚ/689/2008 και/ ή των οικείων Κανο νισμών, αναφορικά με τις οποίες ο Υπουργός δύναται να επιβάλει διοικητικά πρόστιμα που δεν υπερβαίνουν τα είκοσι χιλιάδες ευρώ (€20.000)· και\n(ιβ)τον καθορισμό του ύψους των τελών, των οποίων η καταβολή προβλέπεται από τον κανονισμό ΕΚ/689/2008, τον παρόντα Νόμο και/ ή από Κανονισμούς που εκδίδονται δυνάμει αυτού.\n(3) Κανονισμοί που εκδίδονται δυνάμει του παρόντος Νόμου, μπορούν -\n(α)να προβλέπουν την έκδοση διαταγμάτων ή γνωστοποιήσεων για τον καθορισμό τεχνικών θεμάτων για την καλύτερη εφαρμογή του παρόντος Νόμου και των Κανονισμών που εκδίδονται δυνάμει αυτού·\n(β)να επιτρέπουν την αναφορά σε συγκεκριμένα έγγραφα, κώδικες ή αρχεία, τα οποία πρέπει να διατίθενται προς επιθεώρηση σε συγκεκριμένο μέρος και αντίγραφο των οποίων πρέπει να διατίθεται σε όσους το ζητούν, σύμφωνα με όρους που καθορίζονται στους Κανονισμούς.\n(4) Κανονισμοί που εκδίδονται δυνάμει των παραγράφων (α), (β), (γ), (δ), (ε), (στ), (ζ) και (η) του εδαφίου (2), μπορούν να προβλέπουν τη θέσπιση ποινικών αδικημάτων για παράβαση των διατάξεών τους, αναφορικά με τα οποία δύναται να επιβληθούν ποινές που δεν υπερβαίνουν αυτές που προβλέπονται στον παρόντα Νόμο."
    },
    {
      "provision_ref": "sec4",
      "chapter": "ΜΕΡΟΣ ΙΙ ΕΚΔΟΣΗ ΚΑΝΟΝΙΣΜΩΝ ΚΑΙ ΔΙΑΤΑΓΜΑΤΩΝ",
      "section": "4",
      "title": "Άρθρο 4: Τροποποίηση παραρτημάτων",
      "content": "4. Ο Υπουργός δύναται, με διάταγμα που δημοσιεύεται στην Επίσημη Εφημερίδα της Δημοκρατίας, να τροποποιεί ή να αντικαθιστά οποιοδήποτε από τα τεχνικού περιεχομένου παραρτήματα των Κανονισμών, οι οποίοι εκδίδονται δυνάμει του παρόντος Νόμου."
    },
    {
      "provision_ref": "sec5",
      "chapter": "ΜΕΡΟΣ ΙΙΙ ΠΑΓΚΥΠΡΙΟ ΣΥΜΒΟΥΛΙΟ ΧΗΜΙΚΩΝ ΟΥΣΙΩΝ, ΠΑΡΑΣΚΕΥΑΣΜΑΤΩΝ ΚΑΙ ΠΡΟΪΟΝΤΩΝ",
      "section": "5",
      "title": "Άρθρο 5: Εγκαθίδρυση Παγκύπριου Συμβουλίου Χημικών Ουσιών, Παρασκευασμάτων και Προϊόντων",
      "content": "5.-(1) Ο Υπουργός, με διάταγμα που δημοσιεύεται στην Επίσημη Εφημερίδα της Δημοκρατίας, καθορίζει τη σύσταση του Παγκύπριου Συμβουλίου Χημικών Ουσιών, Παρασκευασμάτων και Προϊόντων, το οποίο συμβουλεύει τον Υπουργό πάνω σε θέματα καλύτερης διαχείρισης χημικών ουσιών, παρασκευασμάτων και προϊόντων.\n(2) Το Συμβούλιο που αναφέρεται στο εδάφιο (1) εγκαθιδρύεται με βάση τις διατάξεις των άρθρων 6, 7 και 8."
    },
    {
      "provision_ref": "sec6",
      "chapter": "ΜΕΡΟΣ ΙΙΙ ΠΑΓΚΥΠΡΙΟ ΣΥΜΒΟΥΛΙΟ ΧΗΜΙΚΩΝ ΟΥΣΙΩΝ, ΠΑΡΑΣΚΕΥΑΣΜΑΤΩΝ ΚΑΙ ΠΡΟΪΟΝΤΩΝ",
      "section": "6",
      "title": "Άρθρο 6: Σύσταση Παγκύπριου Συμβουλίου Χημικών Ουσιών, Παρασκευασμάτων και Προϊόντων",
      "content": "6.-(1) Καθιδρύεται Συμβούλιο το οποίο καλείται «Παγκύπριο Συμβούλιο Χημικών Ουσιών, Παρασκευασμάτων και Προϊόντων». Στο Συμβούλιο αυτό συμμετέχει ο Διευθυντής του Τμήματος Επιθεώρησης Εργασίας του Υπουργείου Εργασίας και Κοινωνικών Ασφαλίσεων και ένας εκπρόσωπος από το καθένα από τα ακόλουθα Υπουργεία και Οργανισμούς:\n(α)Υπουργείο Γεωργίας, Φυσικών Πόρων και Περιβάλλοντος·\n(β)Υπουργείο Υγείας·\n(γ)Υπουργείο Εσωτερικών·\n(δ)Υπουργείο Εμπορίου, Βιομηχανίας και Τουρισμού·\n(ε)Υπουργείο Συγκοινωνιών και Έργων·\n(στ)Υπουργείο Οικονομικών·\n(ζ)Επιστημονικό και Τεχνικό Επιμελητήριο Κύπρου·\n(η)Ομοσπονδία Περιβαλλοντικών και Οικολογικών Οργανώσεων Κύπρου·\n(θ)Παγκύπριος Σύνδεσμος Καταναλωτών·\n(ι)Παγκύπρια Ένωση Καταναλωτών και Ποιότητας Ζωής·\n(ια)Παγκύπρια Ένωση Επιστημόνων Χημικών·\n(ιβ)Παγκύπρια Εργατική Ομοσπονδία·\n(ιγ)Συνομοσπονδία Εργαζομένων Κύπρου·\n(ιδ)Δημοκρατική Εργατική Ομοσπονδία Κύπρου·\n(ιε)Ομοσπονδία Εργοδοτών Κύπρου· και\n(ιστ)Κυπριακό Εμπορικό και Βιομηχανικό Επιμελητήριο.\n(2) (α) Για τον κάθε εκπρόσωπο ορίζεται από το κάθε Υπουργείο ή Οργανισμό και ένας αναπληρωτής εκπρόσωπος, ο οποίος συμμετέχει στις συνεδρίες του Συμβουλίου μόνο εάν δεν μπορεί να συμμετάσχει ο εκπρόσωπος.\n(β) Ο Υπουργός, με γνωστοποίηση που δημοσιεύεται στην Επίσημη Εφημερίδα της Δημοκρατίας, δημοσιοποιεί τα ονόματα τόσο των εκπροσώπων όσο και των αναπληρωτών τους καθώς και τις περιόδους της θητείας τους.\n(3) Το Συμβούλιο τελεί υπό την προεδρία του Διευθυντή του Τμήματος Επιθεώρησης Εργασίας του Υπουργείου Εργασίας και Κοινωνικών Ασφαλίσεων."
    },
    {
      "provision_ref": "sec7",
      "chapter": "ΜΕΡΟΣ ΙΙΙ ΠΑΓΚΥΠΡΙΟ ΣΥΜΒΟΥΛΙΟ ΧΗΜΙΚΩΝ ΟΥΣΙΩΝ, ΠΑΡΑΣΚΕΥΑΣΜΑΤΩΝ ΚΑΙ ΠΡΟΪΟΝΤΩΝ",
      "section": "7",
      "title": "Άρθρο 7: Λειτουργία Συμβουλίου",
      "content": "7. Οι συνεδρίες του Συμβουλίου συγκαλούνται από τον Πρόεδρο, ο οποίος διευθύνει τις εργασίες της, καταρτίζει την ημερήσια διάταξη κάθε συνεδρίασης και μεριμνά ώστε αυτή, μαζί με γραπτή πρόσκληση, να κοινοποιείται σε κάθε μέλος τουλάχιστον επτά (7) ημέρες πριν από την ημέρα της συνεδρίας."
    },
    {
      "provision_ref": "sec8",
      "chapter": "ΜΕΡΟΣ ΙΙΙ ΠΑΓΚΥΠΡΙΟ ΣΥΜΒΟΥΛΙΟ ΧΗΜΙΚΩΝ ΟΥΣΙΩΝ, ΠΑΡΑΣΚΕΥΑΣΜΑΤΩΝ ΚΑΙ ΠΡΟΪΟΝΤΩΝ",
      "section": "8",
      "title": "Άρθρο 8: Αρμοδιότητες Συμβουλίου",
      "content": "8. Το Συμβούλιο έχει αρμοδιότητα -\n(α)να συμβουλεύει τον Υπουργό για ζητήματα πρόληψης ατυχημάτων και επικίνδυνων συμβάντων για το κοινό και το περιβάλλον, που μπορεί να προκληθούν από ουσίες, παρασκευάσματα, ενδιάμεσα προϊόντα και/ ή χημικά προϊόντα·\n(β)να αναπτύσσει, διαδίδει και διατηρεί τις δραστηριότητες, οι οποίες επηρεάζουν ή δημιουργούν τις προϋποθέσεις για τη βελτίωση της προστασίας του κοινού, των εργαζομένων και του περιβάλλοντος από την έκθεση σε ουσίες, παρασκευάσματα, ενδιάμεσα προϊόντα και/ ή χημικά προϊόντα και τη χρήση αυτών·\n(γ)να υποβάλλει στον Υπουργό προτάσεις ή εισηγήσεις για τα μέτρα που πρέπει να λαμβάνονται για την προστασία του κοινού, των εργαζομένων και του περιβάλλοντος από την έκθεση σε ουσίες, παρασκευάσματα, ενδιάμεσα προϊόντα και/ ή χημικά προϊόντα και τη χρήση αυτών· και/ ή\n(δ)να συμβουλεύει τον Υπουργό αναφορικά με τη σύνταξη ή αναθεώρηση νομοθεσίας, υπό το φως της γνώσης και πείρας που αποκτήθηκε από τη μελέτη των τοπικών συνθηκών, των διεθνών εξελίξεων και της τεχνολογικής προόδου."
    },
    {
      "provision_ref": "sec9",
      "chapter": "ΜΕΡΟΣ IV ΔΙΟΙΚΗΣΗ ΚΑΙ ΕΦΑΡΜΟΓΗ",
      "section": "9",
      "title": "Άρθρο 9: Καθορισμός αρμόδιας αρχής",
      "content": "9. Για σκοπούς εφαρμογής -\n(α)του κανονισμού REACH,\n(β)του κανονισμού ΕΚ/689/2008,\n(γ)του κανονισμού ΕΚ/340/2008,\n(δ)του κανονισμού ΕΚ/440/2008, και\n(ε)του παρόντος Νόμου,\nαρμόδια αρχή είναι ο Υπουργός."
    },
    {
      "provision_ref": "sec10",
      "chapter": "ΜΕΡΟΣ IV ΔΙΟΙΚΗΣΗ ΚΑΙ ΕΦΑΡΜΟΓΗ",
      "section": "10",
      "title": "Άρθρο 10: Αρχιεπιθεωρητής και Επιθεωρητές",
      "content": "10.-(1) Ο Υπουργός, με γνωστοποίηση που δημοσιεύεται στην Επίσημη Εφημερίδα της Δημοκρατίας, ορίζει λειτουργούς του Υπουργείου του ως Επιθεωρητές, για σκοπούς εποπτείας, επιθεώρησης, ελέγχου και εφαρμογής του κανονισμού REACH, του κανονισμού ΕΚ/689/2008, του παρόντος Νόμου και/ ή των δυνάμει αυτού εκδιδομένων Κανονισμών και διαταγμάτων.\n(2) Ο Υπουργός, με γνωστοποίηση που δημοσιεύεται στην Επίσημη Εφημερίδα της Δημοκρατίας, ορίζει ένα εκ των Επιθεωρητών που ορίζονται δυνάμει του εδαφίου (1) ως Αρχιεπιθεωρητή.\n(3) Ο Υπουργός, με γνωστοποίηση που δημοσιεύεται στην Επίσημη Εφημερίδα της Δημοκρατίας, δύναται να εξουσιοδοτεί γραπτώς οποιαδήποτε πρόσωπα, που δεν υπηρετούν στη δημόσια υπηρεσία, τα οποία κρίνει ότι κατέχουν τα κατάλληλα προσόντα, να ασκούν τέτοιες από τις εξουσίες και τα καθήκοντα των Επιθεωρητών και να υπόκεινται σε τέτοιους όρους, όπως καθορίζονται στην εξουσιοδότηση.\n(4) Ο Αρχιεπιθεωρητής ρυθμίζει τον τρόπο με τον οποίο οι Επιθεωρητές εκτελούν τα καθήκοντα και ασκούν τις εξουσίες που τους παρέχονται, με βάση τις διατάξεις του άρθρου 11.\n(5) Ο Υπουργός δύναται να διορίσει αναπληρωτή Αρχιεπιθεωρητή, ο οποίος αντικαθιστά τον Αρχιεπιθεωρητή σε περίπτωση απουσίας, ασθένειας ή ανικανότητας αυτού.\n(6) Κάθε Επιθεωρητής εφοδιάζεται με κατάλληλη ταυτότητα, την οποία οφείλει να επιδεικνύει κατά την άσκηση των καθηκόντων του.\n(7) Καμία ευθύνη δεν καταλογίζεται σε οποιοδήποτε Επιθεωρητή για οποιαδήποτε πράξη ή απόφασή του, η οποία έγινε ή λήφθηκε καλόπιστα μέσα στα πλαίσια της άσκησης από αυτόν των προβλεπομένων από τον παρόντα Νόμο εξουσιών, αρμοδιοτήτων ή καθηκόντων του."
    },
    {
      "provision_ref": "sec11",
      "chapter": "ΜΕΡΟΣ IV ΔΙΟΙΚΗΣΗ ΚΑΙ ΕΦΑΡΜΟΓΗ",
      "section": "11",
      "title": "Άρθρο 11: Εξουσίες εισόδου και επιθεώρησης",
      "content": "11.-(1) Κάθε Επιθεωρητής έχει εξουσία -\n(α)να εισέρχεται ελεύθερα και χωρίς προειδοποίηση σε οποιοδήποτε υποστατικό, στο οποίο έχει εύλογη αιτία να πιστεύει ότι διεξάγεται δραστηριότητα ή διεργασία -\n(i) κατά παράβαση του κανονισμού REACH, του κανονισμού ΕΚ/689/2008, του παρόντος Νόμου και/ ή των δυνάμει αυτού εκδιδομένων Κανονισμών και διαταγμάτων, και/ ή\n(ii) η οποία είναι δυνατόν να προκαλέσει κίνδυνο σοβαρής προσωπικής βλάβης ή σοβαρής βλάβης στο περιβάλλον:\nΝοείται ότι, η είσοδος σε κατοικία γίνεται μόνο με την εξασφάλιση της συγκατάθεσης του ενοίκου της ή με δικαστικό ένταλμα·\n(β)να ασκεί το ανωτέρω δικαίωμα εισόδου και ελέγχου, συνοδευόμενος από αστυνομικό αν έχει εύλογη αιτία να αναμένει παρεμπόδιση στην άσκηση των εξουσιών του·\n(γ)να συνοδεύεται από οποιοδήποτε άλλο πρόσωπο που θα το βοηθήσει στην άσκηση των καθηκόντων του, καθώς και να φέρει και να χρησιμοποιεί οποιοδήποτε εξοπλισμό ή οποιαδήποτε υλικά απαιτούνται για την άσκηση των εξουσιών του ·\n(δ)να διεξάγει ή να φροντίζει για τη διεξαγωγή των δοκιμών, αναλύσεων και μετρήσεων που κρίνονται αναγκαίες για την άσκηση των εξουσιών του·\n(ε)να επιθεωρεί, να εξετάζει και να ελέγχει τη λειτουργία οποιασδήποτε εγκατάστασης, εξοπλισμού ή αντικειμένου που βρίσκει στο υποστατικό και να προβαίνει στις μετρήσεις και στη λήψη φωτογραφιών που κρίνει αναγκαίες για τη σωστή άσκηση των εξουσιών του·\n(στ)να δίνει οδηγίες ώστε το υποστατικό ή οποιοδήποτε μέρος αυτού ή οποιοσδήποτε εξοπλισμός, αντικείμενο, ουσία, παρασκεύασμα, ενδιάμεσο προϊόν, χημικό προϊόν ή επικίνδυνη ουσία και/ ή παρασκεύασμα μέσα σε αυτό, ανάλογα με την περίπτωση, να παραμένουν όπως έχουν, για όσο χρόνο θεωρείται εύλογα αναγκαίος για τη διεξαγωγή οποιασδήποτε δοκιμής, μέτρησης, εξέτασης και ελέγχου, όπως αναφέρεται στις παραγράφους (δ) και (ε)·\n(ζ)να ζητά την παρουσίαση για επιθεώρηση οποιωνδήποτε βιβλίων, εγγράφων ή άλλων στοιχείων σε γραπτή ή ηλεκτρονική μορφή, τα οποία έχει εύλογη αιτία να πιστεύει ότι περιέχουν πληροφορίες σχετιζόμενες με το σκοπό της διερεύνησής του·\n(η)να ζητά από -\n(i) εισαγωγέα, εξαγωγέα, παραγωγό αντικειμένου, καταχωρίζοντα, παρασκευαστή, μεταγενέστερο χρήστη, διανομέα, προμηθευτή ουσίας ή παρασκευάσματος, προμηθευτή αντικειμένου, αποδέκτη ουσίας ή παρασκευάσματος και/ ή αποδέκτη ενός αντικειμένου, ανάλογα με την περίπτωση,\n(ii) οποιοδήποτε πρόσωπο, το οποίο βρίσκει στο υποστατικό, και\n(iii) οποιοδήποτε πρόσωπο, για το οποίο έχει εύλογη αιτία να πιστεύει ότι είχε απασχοληθεί στο υποστατικό ή είχε σχέση με τη δραστηριότητα οποιωνδήποτε από τα πρόσωπα που αναφέρονται στην υποπαράγραφο (i) οποτεδήποτε κατά τη διάρκεια των προηγούμενων τριών μηνών,\nνα δίνει οποιεσδήποτε πληροφορίες, είτε προφορικώς είτε γραπτώς, που μπορεί να έχει ή στις οποίες έχει πρόσβαση και που είναι σχετικές με το σκοπό της έρευνας ή διερεύνησής του· και/ ή\n(θ)να λαμβάνει και να μεταφέρει οποιοδήποτε αντικείμενο ή οποιο δήποτε δείγμα οποιασδήποτε ουσίας, παρασκευάσματος, ενδιάμεσου προϊόντος, χημικού προϊόντος, επικίνδυνης ουσίας και/ ή παρασκευάσματος, ανάλογα με την περίπτωση, το οποίο δυνατό να απαιτείται για σκοπούς περαιτέρω διερεύνησης ή μαρτυρίας κατά την εκδίκαση αδικήματος που διαπράττεται κατά παρά βαση του κανονισμού REACH, του κανονισμού ΕΚ/689/2008, του παρόντος Νόμου και/ ή Κανονισμών που εκδίδονται με βάση αυτόν, και να ζητά από οποιοδήποτε από τα πρόσωπα που αναφέρονται στην υποπαράγραφο (i) της παραγράφου (η), το διαχειριστή ή τον κάτοχο του υποστατικού ή οποιοδήποτε από τους αντιπροσώπους τους ή τους εργοδοτουμένους τους, που είναι παρόντες -\n(i) να του παράσχει ασφαλή πρόσβαση προς οποιοδήποτε μέρος του υποστατικού, και/ ή\n(ii) να θέσει στη διάθεσή του οποιαδήποτε ευλόγως διαθέσιμα μέσα για τη διεξαγωγή οποιωνδήποτε δοκιμών, μετρήσεων, επιθεωρήσεων ή εξετάσεων που κρίνονται αναγκαίες για τους σκοπούς της διερεύνησης.\n(2) Το χρηματικό ποσό για τη διεξαγωγή των δοκιμών, μετρήσεων, επιθεωρήσεων ή εξετάσεων που αναφέρονται στην υποπαράγραφο (ii), της παραγράφου (θ), του εδαφίου (1), καταβάλλεται από τα πρόσωπα που αναφέρονται στην υποπαράγραφο (i) της παραγράφου (η) του εδαφίου (1), ανάλογα με την περίπτωση, το διαχειριστή ή κάτοχο του υποστατικού ή αντιπρόσωπο αυτών."
    },
    {
      "provision_ref": "sec12",
      "chapter": "ΜΕΡΟΣ IV ΔΙΟΙΚΗΣΗ ΚΑΙ ΕΦΑΡΜΟΓΗ",
      "section": "12",
      "title": "Άρθρο 12: Κατάσχεση",
      "content": "12.-(1) Σε περίπτωση που Επιθεωρητής έχει εύλογη αιτία να πιστεύει ότι υπήρξε παράβαση οποιασδήποτε διάταξης του κανονισμού REACH, του κανονισμού ΕΚ/689/2008, του παρόντος Νόμου και/ ή Κανονισμών που εκδίδονται με βάση αυτόν, αναφορικά με οποιαδήποτε ουσία, παρασκεύασμα, αντικείμενο, ενδιάμεσο προϊόν, χημικό προϊόν, επικίνδυνη ουσία και/ ή παρασκεύασμα, ανάλογα με την περίπτωση, δύναται να κατάσχει και να κατακρατήσει αυτά για να διαπιστωθεί, με δοκιμή ή άλλως πως, οποιαδήποτε τέτοια παράβαση.\n(2) Ο Επιθεωρητής δύναται να κατάσχει και να κατακρατεί-\n(α) οποιαδήποτε ουσία, παρασκεύασμα, αντικείμενο, ενδιάμεσο προϊόν, χημικό προϊόν, επικίνδυνη ουσία και/ ή παρασκεύασμα, ανάλογα με την περίπτωση, ή τεκμήριο, που περιέχει πληροφορίες, για τα οποία έχει εύλογη αιτία να υποπτεύεται ότι μπορεί να χρειαστούν για αποδεικτικούς σκοπούς σε ποινική διαδικασία·\n(β) οποιαδήποτε ουσία, παρασκεύασμα, αντικείμενο, ενδιάμεσο προϊόν, χημικό προϊόν, επικίνδυνη ουσία και/ ή παρασκεύασμα, ανάλογα με την περίπτωση, για το οποίο έχει εύλογη αιτία να υποπτεύεται ότι δυνατό να υπόκειται σε δήμευση, δυνάμει των διατάξεων του άρθρου 16."
    },
    {
      "provision_ref": "sec13",
      "chapter": "ΜΕΡΟΣ IV ΔΙΟΙΚΗΣΗ ΚΑΙ ΕΦΑΡΜΟΓΗ",
      "section": "13",
      "title": "Άρθρο 13: Ειδοποίηση κατάσχεσης",
      "content": "13. Σε περίπτωση κατάσχεσης οποιωνδήποτε ουσιών, παρασκευασμάτων, αντικειμένων, ενδιάμεσων προϊόντων, χημικών προϊόντων, επικίνδυνων ουσιών και/ ή παρασκευασμάτων, ανάλογα με την περίπτωση, ή σχετικών με αυτά πληροφοριών, δυνάμει των διατάξεων του άρθρου 12, ο Επιθεωρητής οφείλει να πληροφορεί το πρόσωπο, από το οποίο αυτά έχουν κατασχεθεί, ότι αυτά έχουν κατασχεθεί και/ ή κατακρατηθεί, ανάλογα με την περίπτωση, παραθέτοντας τα μέτρα, στα οποία προτίθεται να προβεί, ώστε να διασφαλισθεί ότι ολόκληρη η ποσότητα ή η ποιότητα αυτών δε θα διαφοροποιηθεί."
    },
    {
      "provision_ref": "sec14",
      "chapter": "ΜΕΡΟΣ IV ΔΙΟΙΚΗΣΗ ΚΑΙ ΕΦΑΡΜΟΓΗ",
      "section": "14",
      "title": "Άρθρο 14: Ειδοποίηση συμμόρφωσης",
      "content": "14.-(1) Ο Επιθεωρητής, αφού διαπιστώσει μη συμμόρφωση ουσίας, παρασκευάσματος, αντικειμένου, ενδιάμεσου προϊόντος, χημικού προϊόντος, επικίνδυνης ουσίας και/ ή παρασκευάσματος, προς οποιαδήποτε διάταξη του κανονισμού REACH, του κανονισμού ΕΚ/689/2008 και/ ή του παρόντος Νόμου ή Κανονισμών που εκδίδονται δυνάμει αυτού, ανάλογα με την περίπτωση, επιδίδει ειδοποίηση στον παραγωγό αντικειμένου, στον καταχωρίζοντα, στον παρασκευαστή, στο μεταγενέστερο χρήστη, στο διανομέα, στον προμηθευτή ουσίας ή παρασκευάσματος, στον προμηθευτή αντικειμένου, στον αποδέκτη ουσίας ή παρασκευάσματος και/ ή στον αποδέκτη ενός αντικειμένου, ανάλογα με την περίπτωση, με την οποία του επισημαίνει την παράβαση και τον καλεί να συμμορφωθεί με τις εν λόγω διατάξεις, μέσα σε χρονικό διάστημα που καθορίζεται στην ειδοποίηση, ανάλογα με τη φύση της παράβασης.\n(2) Η ειδοποίηση συμμόρφωσης περιλαμβάνει-\n(α)τα μέτρα, στα οποία ο Επιθεωρητής προτίθεται να προβεί, σε περίπτωση που το πρόσωπο που αναφέρεται στο εδάφιο (1), δε συμμορφωθεί·\n(β)τα μέτρα, στα οποία το πρόσωπο που αναφέρεται στο εδάφιο (1), οφείλει να προβεί για να θεωρηθεί ότι συμμορφώνεται με τις διατάξεις του κανονισμού REACH, του κανονισμού ΕΚ/689/2008, του παρόντος Νόμου και/ ή Κανονισμών που εκδίδονται με βάση αυτόν· και\n(γ)την προθεσμία, εντός της οποίας το πρόσωπο που αναφέρεται στο εδάφιο (1), οφείλει να παραθέσει τις απόψεις του για την εν λόγω παράβαση, είτε προφορικώς είτε γραπτώς, στον Επιθεωρητή.\n(3) Σε περίπτωση μη συμμόρφωσης, ο Επιθεωρητής δύναται να λάβει οποιαδήποτε μέτρα κρίνει κατάλληλα, ανάλογα με τη σοβαρότητα της παράβασης, περιλαμβανομένης της ειδοποίησης αναστολής ή απόσυρσης."
    },
    {
      "provision_ref": "sec15",
      "chapter": "ΜΕΡΟΣ IV ΔΙΟΙΚΗΣΗ ΚΑΙ ΕΦΑΡΜΟΓΗ",
      "section": "15",
      "title": "Άρθρο 15: Ειδοποίηση αναστολής ή απόσυρσης",
      "content": "15.-(1) Σε περίπτωση που ο Επιθεωρητής ενεργεί σύμφωνα με το εδάφιο (3) του άρθρου 14, επιδίδει στο πρόσωπο που αναφέρεται στο εδάφιο (1) του άρθρου 14 -\n(α) ειδοποίηση αναστολής, η οποία απαγορεύει στο πρόσωπο στο οποίο επιδίδεται, για περίοδο που καθορίζει σε αυτή, όχι όμως μεγαλύτερη των έξι (6) μηνών από την ημερομηνία επίδοσης της ειδοποίησης, την παρασκευή και/ ή τη διάθεση στην αγορά της ουσίας, του παρασκευάσματος, του αντικειμένου, του ενδιάμεσου προϊόντος, του χημικού προϊόντος, της επικίνδυνης ουσίας και/ ή του παρασκευάσματος, ανάλογα με την περίπτωση, χωρίς τη συγκατάθεση του Επιθεωρητή, ή\n(β) ειδοποίηση απόσυρσης της ουσίας, του παρασκευάσματος, του αντικειμένου, του ενδιάμεσου προϊόντος, του χημικού προϊόντος, της επικίνδυνης ουσίας και/ή του παρασκευάσματος, ανάλογα με την περίπτωση.\n(2) Η ειδοποίηση αναστολής ή απόσυρσης οφείλει να -\n(α)περιγράφει την ουσία, το παρασκεύασμα, το αντικείμενο, το ενδιάμεσο προϊόν, το χημικό προϊόν, την επικίνδυνη ουσία και/ ή το παρασκεύασμα, ανάλογα με την περίπτωση, με τρόπο που να διακριβώνεται επακριβώς η ταυτότητά του· και\n(β)εκθέτει τους λόγους, για τους οποίους επιδίδεται και τους λόγους για τους οποίους ο Επιθεωρητής θεωρεί ότι υπήρξε παράβαση των διατάξεων του κανονισμού REACH, του κανονισμού ΕΚ/689/2008, του παρόντος Νόμου και/ ή Κανονισμών που εκδίδονται με βάση αυτόν, ανάλογα με την περίπτωση.\n(3) Η ειδοποίηση αναστολής ή απόσυρσης, η οποία επιδίδεται από τον Επιθεωρητή δυνάμει του εδαφίου (1), δύναται να απαιτεί από το πρόσωπο προς το οποίο επιδίδεται, να τηρεί ενήμερο τον Επιθεωρητή για το χώρο στον οποίο βρίσκεται η ουσία, το παρασκεύασμα, το αντικείμενο, το ενδιάμεσο προϊόν, το χημικό προϊόν, την επικίνδυνη ουσία και/ ή το παρασκεύασμα, ανάλογα με την περίπτωση, κατά το χρονικό διάστημα της αναστολής ή απόσυρσης."
    },
    {
      "provision_ref": "sec16",
      "chapter": "ΜΕΡΟΣ IV ΔΙΟΙΚΗΣΗ ΚΑΙ ΕΦΑΡΜΟΓΗ",
      "section": "16",
      "title": "Άρθρο 16: Δήμευση κατόπιν διατάγματος δικαστηρίου",
      "content": "16.-(1) Ανεξάρτητα από -\n(α)την έγερση οποιασδήποτε ποινικής δίωξης για αδίκημα, αναφορικά με παράβαση των διατάξεων του κανονισμού REACH, του κανονισμού ΕΚ/689/2008, του παρόντος Νόμου και/ ή Κανονισμών που εκδίδονται με βάση αυτόν, ή\n(β)την επιβολή διοικητικού προστίμου για παράβαση των διατάξεων του κανονισμού REACH, του κανονισμού ΕΚ/689/2008, του παρόντος Νόμου και/ ή Κανονισμών που εκδίδονται με βάση αυτόν,\nο Επιθεωρητής δύναται να αποταθεί σε δικαστήριο ζητώντας την έκδοση διατάγματος για τη δήμευση οποιασδήποτε ουσίας, παρασκευάσματος, αντικειμένου, ενδιάμεσου προϊόντος, χημικού προϊόντος, επικίνδυνης ουσίας και/ ή παρασκευάσματος, ανάλογα με την περίπτωση, για το λόγο ότι δε συμμορφώνεται με τις διατάξεις του κανονισμού REACH, του κανονισμού ΕΚ/689/2008, του παρόντος Νόμου και/ ή Κανονισμών που εκδίδονται με βάση αυτόν.\n(2) Μετά την υποβολή αίτησης δυνάμει του παρόντος άρθρου, το δικαστήριο εκδίδει διάταγμα δήμευσης, αν ικανοποιηθεί ότι -\n(α)πράγματι η ουσία, το παρασκεύασμα, το αντικείμενο, το ενδιάμεσο προϊόν, το χημικό προϊόν, η επικίνδυνη ουσία και/ ή το παρασκεύασμα, δεν συμμορφώνεται με τις διατάξεις του κανονισμού REACH, του κανονισμού ΕΚ/689/2008, του παρόντος Νόμου και/ ή Κανονισμών που εκδίδονται με βάση αυτόν, ανάλογα με την περίπτωση· και\n(β)το πρόσωπο, στο οποίο επιδόθηκε ειδοποίηση αναστολής ή απόσυρσης, δε συμμορφώνεται με αυτή.\n(3) Στην περίπτωση δήμευσης, δυνάμει των διατάξεων του παρόντος άρθρου, η οικεία ουσία, το παρασκεύασμα, το αντικείμενο, το ενδιάμεσο προϊόν, το χημικό προϊόν, η επικίνδυνη ουσία και/ ή το παρασκεύασμα, ανάλογα με την περίπτωση, δύνανται να καταστραφούν, σύμφωνα με οδηγίες του δικαστηρίου."
    },
    {
      "provision_ref": "sec17",
      "chapter": "ΜΕΡΟΣ V ΑΔΙΚΗΜΑΤΑ ΚΑΙ ΠΟΙΝΕΣ",
      "section": "17",
      "title": "Άρθρο 17: Αδικήματα και ποινές",
      "content": "17.-(1) Πρόσωπο είναι ένοχο αδικήματος, αν:\n(α) σκόπιμα καθυστερεί ή παρεμποδίζει Επιθεωρητή κατά την εκτέλεση των καθηκόντων του ή την άσκηση των εξου σιών του δυνάμει του παρόντος Νόμου ή των Κανονισμών που εκδίδονται με βάση αυτόν·\n(β) παρεμποδίζει ή αποπειράται να παρεμποδίσει οποιοδήπο τε αστυνομικό ή άλλο πρόσωπο που εισήλθε σε υποστατικό μαζί με Επιθεωρητή, σύμ φωνα με τις παραγράφους (β) και/ ή (γ), του εδαφίου (1), του άρθρου 11, αντίστοιχα, το οποίο παρέχει βοήθεια στον Επιθεωρητή·\n(γ) παραλείπει να συμμορφωθεί προς οδηγία που δίδεται σ' αυτό από τον Επιθεωρητή δυνάμει της παραγράφου (στ), του εδαφίου (1), του άρθρου 11·\n(δ) παραλείπει να παρουσιάσει μέσα σε εύλογο χρονικό διά στημα οποιοδήποτε βιβλίο, έγγραφο ή άλλο στοιχείο, σε γραπτή ή ηλεκτρονική μορφή, που απαιτείται να παρουσιάσει δυνάμει της παραγράφου (ζ), του εδαφίου (1), του άρθρου 11, εκτός αν αποδείξει ότι:\n(i) δεν γνώριζε ότι την παρουσίαση την απαιτούσε Επιθεωρητής, ή\n(ii) δεν είχε πρόσβαση στο βιβλίο, έγγραφο ή στοιχείο, ή\n(iii) δεν είχε εξουσία να το πάρει·\n(ε) ενώ είναι πρόσωπο που εμπίπτει στις διατάξεις των υπο παραγράφων (i), (ii) και/ ή (iii), της παραγράφου (η), του εδαφίου (1), του άρ θρου 11, παραλείπει να δώσει, μέσα σε εύλογο χρονικό διά στημα, πληροφορίες που του ζητήθηκαν από Επιθεωρητή, σύμφωνα με την εν λόγω παράγραφο, ή δίδει πληροφορίες που είναι αναληθείς ή λανθασμένες ή ατε λείς·\n(στ) ενώ είναι ένα από τα πρόσωπα ή εμπίπτει στις κατηγορίες των προσώπων που αναφέρονται στην παράγραφο (θ), του εδαφίου (1), του άρθρου 11 παραλείπει, κατόπιν νόμιμης απαίτησης του Επιθεωρητή, μέσα σε εύλογο χρονικό διάστημα -\n(i) να παράσχει στον Επιθεωρητή ή σε οποιοδήποτε πρόσωπο που εισήλθε σε υποστατικό μαζί του, ασφαλή πρόσβαση σε οποιοδήποτε μέρος αυτών, και/ ή\n(ii) να θέσει στη διάθεση του Επιθεωρητή ή οποιουδήπο τε προσώπου, το οποίο εισήλθε σε υποστατικό μαζί του, οποιαδήποτε μέσα για τη διε ξαγωγή δοκιμών, μετρήσεων, επιθεωρήσεων ή εξετάσεων,\nνοουμένου ότι, σε κάθε περίπτωση, έχει την εξουσία να το πράξει και ότι τα μέσα που αναφέρονται στην υποπαρά γραφο (ii), της παραγράφου (θ), του εδαφίου (1), του άρθρου 11 είναι ευλόγως διαθέσι μα·\n(ζ) πλαστογραφεί οποιοδήποτε πιστοποιητικό που απαιτείται δυνάμει ή για τους σκοπούς του κανονισμού REACH, του κανονισμού ΕΚ/689/2008, του κανονισμού ΕΚ/440/2008, του παρόντος Νόμου και/ ή οποιωνδήποτε Κανονισμών και διαταγμάτων εκδίδονται δυνάμει αυτού, ανάλογα με την περίπτωση·\n(η) δίδει ή υπογράφει τέτοιο πιστοποιητικό εν γνώσει του ότι είναι αναληθές σε σχέση με οποιοδήποτε ουσιώδες στοι χείο·\n(θ) εν γνώσει του παρουσιάζει ή χρησιμοποιεί πιστοποιητικό που έχει πλαστογραφηθεί ή είναι ψευδές σε σχέση με οποιοδήποτε ουσιώδες στοιχείο·\n(ι) παρουσιάζει ή χρησιμοποιεί ως αφορώντα οποιοδήποτε πρόσωπο, πιστοποιητικά, τα οποία εν γνώσει του δεν αφο ρούν το εν λόγω πρόσωπο·\n(ια) παριστάνει πρόσωπο που κατονομάζεται σε τέτοιο πιστοποιητικό·\n(ιβ) προσποιείται ψευδώς ότι είναι Επιθεωρητής·\n(ιγ) εσκεμμένα συγκατατίθεται στην πιο πάνω πλαστογράφηση, υπογραφή, χρήση, πλαστοπροσωπία ή προσποίηση·\n(ιδ) εσκεμμένα προβαίνει σε ψευδή καταχώρηση σε κατάλογο, βιβλίο, ειδοποίηση, πιστοποιητικό ή έγγραφο που απαιτεί ται δυνάμει ή για τους σκοπούς του κανονισμού REACH, του κανονισμού ΕΚ/689/2008, του κανονισμού ΕΚ/440/2008, του παρόντος Νόμου και/ ή οποιωνδήποτε Κανονισμών και διαταγμάτων εκδίδονται δυνάμει αυτού, ανάλογα με την περίπτωση·\n(ιε) εσκεμμένα προβαίνει σε ψευδή δήλωση ή υπογράφει ψευδή δήλωση που απαιτείται από, με βάση ή για τους σκοπούς του κανονισμού REACH, του κανονισμού ΕΚ/689/2008, του κανονισμού ΕΚ/440/2008, του παρόντος Νόμου και/ ή οποιωνδήποτε Κανονισμών και διαταγμάτων εκδίδονται δυνάμει αυτού· και/ ή\n(ιστ) εν γνώσει του κάνει χρήση τέτοιας ψευδούς καταχώρισης ή δήλωσης, όπως αναφέρεται στην υποπαράγραφο (ιε) πιο πάνω.\n(2) Πρόσωπο, το οποίο παραβαίνει ειδοποίηση συμμόρφωσης είναι ένοχο αδικήματος και υπόκειται στις ποινές που αναφέρονται στο εδάφιο (4).\n(3) Πρόσωπο, το οποίο παραβαίνει ειδοποίηση αναστολής ή απόσυρσης είναι ένοχο αδικήματος και υπόκειται στις ποινές που αναφέρονται στο εδάφιο (4).\n(4) Πρόσωπο, το οποίο παραβαίνει ή παραλείπει να συμμορφωθεί με τις διατάξεις των εδαφίων (1), (2) και (3) είναι ένοχο αδικήματος και, σε περίπτωση καταδίκης, υπόκειται σε χρηματική ποινή που δεν υπερβαίνει τα ογδόντα χιλιάδες ευρώ (€ 80.000) ή σε φυλάκιση για περίοδο που δεν υπερβαίνει τα δύο (2) χρό νια ή και στις δύο αυτές ποινές.\n(5) Σε περίπτωση δεύτερης ή μεταγενέστερης καταδίκης, τα αδικήματα που αναφέρονται στα εδάφια (1), (2) και (3) τιμωρούνται με χρηματική ποινή που δεν υπερβαίνει τα ογδόντα χιλιάδες ευρώ (€ 80.000) ή σε φυλάκιση για περίοδο που δεν υπερβαίνει τα τέσσερα (4) χρό νια ή και στις δύο αυτές ποινές."
    },
    {
      "provision_ref": "sec18",
      "chapter": "ΜΕΡΟΣ V ΑΔΙΚΗΜΑΤΑ ΚΑΙ ΠΟΙΝΕΣ",
      "section": "18",
      "title": "Άρθρο 18: Ποινική ευθύνη νομικών προσώπων και αξιωματούχων τους",
      "content": "18.-(1) Σε περίπτωση που διαπραχθεί ποινικό αδίκημα, με βάση τις διατάξεις του παρόντος Νόμου και/ ή Κανονισμών που εκδίδονται με βάση αυτόν, από νομικό πρόσωπο και αποδεικνύεται ότι το αδίκημα αυτό έχει διαπραχθεί με την συναίνεση ή τη συμπαιγνία ή αποδίδεται σε παράλειψη προσώπου που είναι διευθύνων σύμβουλος, διευθυντής, γραμματέας ή άλλος αξιωματούχος του νομικού αυτού προσώπου ή πρόσωπο που εμφανίζεται ότι ενεργεί με τέτοια ιδιότητα, τότε το πρόσωπο αυτό, καθώς επίσης και το νομικό πρόσωπο, είναι ένοχοι ποινικού αδικήματος και υπόκεινται σε ποινική δίωξη σε σχέση με το εν λόγω ποινικό αδίκημα.\n(2) Όταν μέλος νομικού προσώπου, χωρίς να είναι διευθύνων σύμβουλος ή διευθυντής, ασκεί αρμοδιότητες διευθύνοντος συμβούλου ή διευθυντή, τότε εφαρμόζεται, σε σχέση με τις πράξεις ή παραλείψεις του, το εδάφιο (1), ως εάν το πρόσωπο αυτό να ήταν διευθύνων σύμβουλος ή διευθυντής του νομικού προσώπου."
    },
    {
      "provision_ref": "sec19",
      "chapter": "ΜΕΡΟΣ V ΑΔΙΚΗΜΑΤΑ ΚΑΙ ΠΟΙΝΕΣ",
      "section": "19",
      "title": "Άρθρο 19: Ανάκτηση δαπανών εκτέλεσης",
      "content": "19. Σε περίπτωση που δικαστήριο καταδικάζει πρόσωπο για οποιοδήποτε από τα ποινικά αδικήματα με βάση τις διατάξεις του άρθρου 17 και/ ή Κανονισμών που εκδίδονται δυνάμει του παρόντος Νόμου ή εκδίδει διάταγμα δήμευσης, δυνάμει των διατάξεων του άρθρου 16, αυτό έχει εξουσία, επιπροσθέτως από οποιαδήποτε άλλη διαταγή για έξοδα ή δαπάνες, να διατάξει το καταδικαζόμενο πρόσωπο να αποζημιώσει τον Υπουργό για οποιαδήποτε δαπάνη, στην οποία υποβλήθηκε ή δυνατό να υποβληθεί -\n(α)σε σχέση με οποιαδήποτε κατάσχεση ή κατακράτηση από ή για λογαριασμό του Υπουργού.\n(β)σε σχέση με τη συμμόρφωση του Υπουργού με οδηγίες του δικαστηρίου για δήμευση.\n(γ)σε σχέση με οποιαδήποτε έξοδα επιβαρύνθηκε ο Υπουργός κατά την ενάσκηση των εξουσιών του, δυνάμει των διατάξεων του παρόντος Νόμου και/ ή Κανονισμών που εκδίδονται δυνάμει αυτού."
    },
    {
      "provision_ref": "sec20",
      "chapter": "ΜΕΡΟΣ V ΑΔΙΚΗΜΑΤΑ ΚΑΙ ΠΟΙΝΕΣ",
      "section": "20",
      "title": "Άρθρο 20: Περιορισμός στην αποκάλυψη πληροφοριών",
      "content": "20.-(1) Χωρίς επηρεασμό των διατάξεων του άρθρου 19, παράγραφος 3 του κανονισμού ΕΚ/689/2008, αποτελεί αδίκημα για οποιοδήποτε πρόσωπο που έχει αποκτήσει πληροφορίες κατά την άσκηση, είτε από το ίδιο είτε από άλλο πρόσωπο, εξουσιών δυνάμει του παρόντος Νόμου να τις αποκαλύπτει, εκτός αν η αποκάλυψη γίνεται:\n(α)με τη συγκατάθεση του προσώπου που έχει το δικαίωμα να χρησιμοποιεί ή να τηρεί το εμπορικό μυστικό,\n(β)για σκοπούς εφαρμογής οποιωνδήποτε διατάξεων, τις οποίες έχει υποχρέωση διά νόμου να εφαρμόζει, και/ ή\n(γ)για σκοπούς ποινικής διαδικασίας.\n(2) Πρόσωπο, το οποίο παραβαίνει ή παραλείπει να συμμορφωθεί με τις διατάξεις του εδαφίου (1), είναι ένοχο αδικήματος και, σε περίπτωση καταδίκης, υπό κειται σε χρηματική ποινή που δεν υπερβαίνει τις ογδόντα χιλιάδες ευρώ (€ 80.000) ή σε φυλάκιση για περίοδο που δεν υπερβαίνει τα δύο (2) χρόνια ή και στις δύο αυτές ποινές.\n(3) Σε περίπτωση δεύτερης ή μεταγενέστερης καταδίκης, τα αδικήματα που αναφέρονται στο εδάφιο (1) τιμωρούνται με χρηματική ποινή που δεν υπερβαίνει τα ογδόντα χιλιάδες ευρώ (€ 80.000) ή σε φυλάκιση για περίοδο που δεν υπερβαίνει τα τέσσερα (4) χρό νια ή και στις δύο αυτές ποινές."
    },
    {
      "provision_ref": "sec21",
      "chapter": "ΜΕΡΟΣ V ΑΔΙΚΗΜΑΤΑ ΚΑΙ ΠΟΙΝΕΣ",
      "section": "21",
      "title": "Άρθρο 21: Δημοσιοποίηση ονομάτων",
      "content": "21. Χωρίς επηρεασμό των διατάξεων του άρθρου 19, παράγραφος 2 του κανονισμού ΕΚ/689/2008, για σκοπούς καλύτερης προστασίας και ενημέρωσης του κοινού, ο Υπουργός δύναται να δημοσιοποιεί πληροφορίες που αφορούν παραβάσεις του κανονισμού REACH, του κανονισμού ΕΚ/689/2008, του παρόντος Νόμου και/ ή οποιωνδήποτε Κανονισμών και διαταγμάτων εκδίδονται δυνάμει αυτού, ανάλογα με την περίπτωση."
    },
    {
      "provision_ref": "sec22",
      "chapter": "ΜΕΡΟΣ V ΑΔΙΚΗΜΑΤΑ ΚΑΙ ΠΟΙΝΕΣ",
      "section": "22",
      "title": "Άρθρο 22: Έναρξη της ισχύος του παρόντος Νόμου",
      "content": "22. Ο παρών Νόμος τίθεται σε ισχύ από την ημερομηνία δημοσίευσής του στην Επίσημη Εφημερίδα της Δημοκρατίας."
    },
    {
      "provision_ref": "sec23",
      "chapter": "ΜΕΡΟΣ V ΑΔΙΚΗΜΑΤΑ ΚΑΙ ΠΟΙΝΕΣ",
      "section": "23",
      "title": "Άρθρο 23: Κατάργηση",
      "content": "23.-(1) Με την έναρξη ισχύος του παρόντος Νόμου, οι περί Επικίνδυνων Ουσιών Νόμοι του 1991 έως 2004 καταργούνται.\n(2) Κανονισμοί, διατάγματα, γνωστοποιήσεις ή άλλης φύσης πράξεις που έγιναν δυνάμει του καταργηθέντος Νόμου που αναφέρεται στο εδάφιο (1), εξακολουθούν να ισχύουν, μέχρις ότου ανακληθούν ή αντικατασταθούν."
    }
  ],
  "definitions": [
    {
      "term": "αεροσκάφος",
      "definition": "που αποδίδει στον όρο αυτό το άρθρο 2 του περί Πολιτικής Αεροπορίας Νόμου",
      "source_provision": "sec2"
    },
    {
      "term": "αστυνομικός",
      "definition": "που αποδίδει στον όρο αυτό το εδάφιο (1) του άρθρου 2 του περί Αστυνομίας Νόμου·",
      "source_provision": "sec2"
    },
    {
      "term": "δικαστήριο",
      "definition": "Επαρχιακό Δικαστήριο αρμόδιας δικαιοδοσίας·",
      "source_provision": "sec2"
    },
    {
      "term": "επικίνδυνες ουσίες και/ ή παρασκευάσματα",
      "definition": "τις ουσίες και/ ή τα παρασκευάσματα, που εμπίπτουν σε μία ή περισσότερες από τις ακόλουθες κατηγορίες, όπως αυτές ορίζονται στο εδάφιο (2)·",
      "source_provision": "sec2"
    },
    {
      "term": "κανονισμός REACH",
      "definition": "τον κανονισμό (ΕΚ) αριθ",
      "source_provision": "sec2"
    },
    {
      "term": "κανονισμός ΕΚ/340/2008",
      "definition": "τον κανονισμό (ΕΚ) αριθ",
      "source_provision": "sec2"
    },
    {
      "term": "κανονισμός ΕΚ/440/2008",
      "definition": "τον κανονισμό (ΕΚ) αριθ",
      "source_provision": "sec2"
    },
    {
      "term": "κανονισμός ΕΚ/689/2008",
      "definition": "τον κανονισμό (ΕΚ) αριθ",
      "source_provision": "sec2"
    },
    {
      "term": "όχημα",
      "definition": "που αποδίδει στον όρο αυτό το άρθρο 2 του περί Έγκρισης Τύπου Οχημάτων Νόμου·",
      "source_provision": "sec2"
    },
    {
      "term": "πλοίο",
      "definition": "που αποδίδει στον όρο αυτό το άρθρο 2 του περί Εμπορικής Ναυτιλίας (Κοινοτικό Σύστημα Παρακολούθησης και Ενημέρωσης Σχετικά με την Κυκλοφορία Πλοίων) Νόμου·",
      "source_provision": "sec2"
    },
    {
      "term": "Υπουργός",
      "definition": "τον Υπουργό Εργασίας και Κοινωνικών Ασφαλίσεων",
      "source_provision": "sec2"
    },
    {
      "term": "εκρηκτικές",
      "definition": "τις στερεές, υγρές, παχύρρευστες ή ζελατινώδεις ουσίες και/ ή παρασκευάσματα, που μπορούν να αντιδράσουν εξώθερμα, με ταυτόχρονη ταχεία έκλυση αερίων, ακόμη και χωρίς την παρουσία ατμοσφαιρικού οξυγόνου και που, υπό καθορισμένες συνθήκες δοκιμής, εκπυρσοκροτούν, αναφλέγονται έντονα και γρήγορα ή εκρήγνυνται υπό την επίδραση θερμότητας και περιορισμού·",
      "source_provision": "sec2"
    },
    {
      "term": "οξειδωτικές",
      "definition": "τις ουσίες και/ ή παρασκευάσματα, τα οποία, όταν έρχονται σε επαφή με άλλες ουσίες και ιδίως εύφλεκτες ουσίες, προκαλούν ισχυρώς εξώθερμη αντίδραση·",
      "source_provision": "sec2"
    },
    {
      "term": "εξαιρετικά εύφλεκτες",
      "definition": "τις ουσίες και/ ή παρασκευάσματα με εξαιρετικά χαμηλό σημείο ανάφλεξης και χαμηλό σημείο ζέσεως, καθώς και αέριες ουσίες και παρασκευάσματα, τα οποία, υπό κανονική θερμοκρασία και πίεση, αναφλέγονται στον αέρα·",
      "source_provision": "sec2"
    },
    {
      "term": "πολύ εύφλεκτες",
      "definition": "τις ουσίες και/ ή παρασκευάσματα, τα οποία -",
      "source_provision": "sec2"
    },
    {
      "term": "εύφλεκτες",
      "definition": "τις υγρές ουσίες και/ ή παρασκευάσματα με πολύ χαμηλό σημείο ανάφλεξης·",
      "source_provision": "sec2"
    },
    {
      "term": "πολύ τοξικές",
      "definition": "τις ουσίες και/ ή τα παρασκευάσματα, οι οποίες, εισερχόμενες στον ανθρώπινο οργανισμό με εισπνοή, κατάποση ή απορρόφηση μέσω του δέρματος ή με οποιοδήποτε άλλο τρόπο, ακόμη και σε ελάχιστη ποσότητα, προκαλούν το θάνατο ή οξείες ή χρόνιες βλάβες της υγείας·",
      "source_provision": "sec2"
    },
    {
      "term": "τοξικές",
      "definition": "τις ουσίες και/ ή τα παρασκευάσματα, οι οποίες, εισερχόμενες στον ανθρώπινο οργανισμό με εισπνοή, κατάποση ή απορρόφηση μέσω του δέρματος ή με οποιοδήποτε άλλο τρόπο, ακόμα και σε μικρές ποσότητες, προκαλούν το θάνατο ή οξείες ή χρόνιες βλάβες της υγείας·",
      "source_provision": "sec2"
    },
    {
      "term": "επιβλαβείς",
      "definition": "τις ουσίες και/ ή τα παρασκευάσματα, οι οποίες, εισερχόμενες στον ανθρώπινο οργανισμό με εισπνοή, κατάποση ή απορρόφηση μέσω του δέρματος ή με οποιοδήποτε άλλο τρόπο, μπορούν να προκαλέσουν το θάνατο ή οξείες ή χρόνιες βλάβες της υγείας·",
      "source_provision": "sec2"
    },
    {
      "term": "διαβρωτικές",
      "definition": "τις ουσίες και/ ή τα παρασκευάσματα, οι οποίες, σε επαφή με ζώντες ιστούς, μπορούν να τους καταστρέψουν·",
      "source_provision": "sec2"
    },
    {
      "term": "ερεθιστικές",
      "definition": "τις μη διαβρωτικές ουσίες και/ ή τα παρασκευάσματα, οι οποίες, με άμεση, παρατεταμένη ή επαναλαμβανόμενη επαφή με το δέρμα ή τους βλεννογόνους, μπορούν να προκαλέσουν φλεγμονές·",
      "source_provision": "sec2"
    },
    {
      "term": "ευαισθητοποιητικές",
      "definition": "τις ουσίες και/ ή τα παρασκευάσματα, οι οποίες, εισερχόμενες στον ανθρώπινο οργανισμό με εισπνοή, κατάποση ή απορρόφηση μέσω του δέρματος ή με οποιοδήποτε άλλο τρόπο, μπορούν να προκαλέσουν τέτοια αντίδραση του οργανισμού (υπερευαισθητοποίηση) ώστε, με περαιτέρω έκθεση σε αυτή την ουσία ή το παρασκεύασμα, να προκαλούνται χαρακτηριστικές επιβλαβείς αντιδράσεις·",
      "source_provision": "sec2"
    },
    {
      "term": "καρκινογόνες",
      "definition": "τις ουσίες και/ ή τα παρασκευάσματα, οι οποίες, εισερχόμενες στον ανθρώπινο οργανισμό με εισπνοή, κατάποση ή απορρόφηση μέσω του δέρματος ή με οποιοδήποτε άλλο τρόπο, μπορούν να προκαλέσουν καρκίνο ή να αυξήσουν τη συχνότητά του·",
      "source_provision": "sec2"
    },
    {
      "term": "μεταλλαξιογόνες",
      "definition": "τις ουσίες και/ ή τα παρασκευάσματα, οι οποίες, εισερχόμενες στον ανθρώπινο οργανισμό με εισπνοή, κατάποση ή απορρόφηση μέσω του δέρματος ή με οποιοδήποτε άλλο τρόπο, μπορούν να προκαλέσουν κληρονομικά γενετικά ελαττώματα ή να αυξήσουν τη συχνότητά τους·",
      "source_provision": "sec2"
    },
    {
      "term": "τοξικές για την αναπαραγωγή",
      "definition": "τις ουσίες και/ ή τα παρασκευάσματα, οι οποίες, εισερχόμενες στον ανθρώπινο οργανισμό με εισπνοή, κατάποση ή απορρόφηση μέσω του δέρματος ή με οποιοδήποτε άλλο τρόπο, μπορούν να προκαλέσουν ή να αυξήσουν τη συχνότητα μη κληρονομικών επιβλαβών φαινομένων στους απογόνους ή να επιδράσουν δυσμενώς στις αναπαραγωγικές λειτουργίες ή δυνατότητες των δύο φύλων· και",
      "source_provision": "sec2"
    },
    {
      "term": "επικίνδυνες για το περιβάλλον",
      "definition": "τις ουσίες και/ ή τα παρασκευάσματα, οι οποίες, αν εισαχθούν στο περιβάλλον, προκαλούν ή μπορεί να προκαλέσουν άμεσο ή μελλοντικό κίνδυνο για ένα ή περισσότερους τομείς του περιβάλλοντος",
      "source_provision": "sec2"
    }
  ]
}
