{
  "id": "cy-law-2017-1-14",
  "type": "statute",
  "title": "Ο περί Διεξαγωγής των Παγκύπριων Εξετάσεων Πρόσβασης στα Ανώτερα και Ανώτατα Εκπαιδευτικά Ιδρύματα (ΑΑΕΙ) της Κύπρου και Ελλάδας Νόμος του 2017 (14(I)/2017)",
  "short_name": "Ν. 2017/1/14",
  "status": "in_force",
  "url": "https://www.cylaw.org/nomoi/enop/non-ind/2017_1_14/full.html",
  "provisions": [
    {
      "provision_ref": "sec1",
      "section": "1",
      "title": "Άρθρο 1: Συνοπτικός τίτλος",
      "content": "1. Ο παρών Νόμος θα αναφέρεται ως ο περί Διεξαγωγής των Παγκύπριων Εξετάσεων Πρόσβασης στα Ανώτερα και Ανώτατα Εκπαιδευτικά Ιδρύματα (ΑΑΕΙ) της Κύπρου και Ελλάδας Νόμος του 2017."
    },
    {
      "provision_ref": "sec2",
      "section": "2",
      "title": "Άρθρο 2: Ερμηνεία",
      "content": "2. Στον παρόντα Νόμο, εκτός αν από το κείμενο προκύπτει διαφορετική έννοια-\n«Αγωνόδικος Επιτροπή» σημαίνει την Επιτροπή που ορίζεται για την αξιολόγηση των υποψηφίων στο εξεταζόμενο μάθημα της πρακτικής δοκιμασίας.\n«αναβαθμολογητής» σημαίνει τον εκπαιδευτικό που είναι εντεταλμένος από την Υπηρεσία Εξετάσεων σε συνεργασία με τις Διευθύνσεις Μέσης Εκπαίδευσης για την επαναξιολόγηση των τετραδίων απαντήσεων των υποψηφίων κάθε μαθήματος του πλαισίου πρόσβασης.\n«αριθμός υποψηφίου» σημαίνει το μοναδικό αριθμό που δίνεται από την Υπηρεσία Εξετάσεων στον υποψήφιο, για τους σκοπούς των Παγκύπριων Εξετάσεων Πρόσβασης, για τη συγκεκριμένη χρονιά που υποβάλλει αίτηση συμμετοχής και βρίσκεται στο δελτίο υποψηφίου.\n«αρμόδια αρχή» σημαίνει τον Υπουργό Παιδείας και Πολιτισμού.\n«βαθμολογητής» σημαίνει τον εκπαιδευτικό που ορίζεται από την Υπηρεσία Εξετάσεων σε συνεργασία με τις Διευθύνσεις Μέσης Εκπαίδευσης για τη βαθμολόγηση των τετραδίων απαντήσεων των υποψηφίων ή των άλλων μορφών αξιολόγησης, που περιλαμβάνονται στα πλαίσια πρόσβασης των Παγκύπριων Εξετάσεων Πρόσβασης.\n«βαθμός κατάταξης» σημαίνει-\n(α) για τα ΑΑΕΙ της Κύπρου, το βαθμό που εξάγεται σε εικοσάβαθμη κλίμακα, ο οποίος προκύπτει από τη γραπτή ή και άλλης μορφής αξιολόγηση του υποψηφίου στα εξεταζόμενα μαθήματα του πλαισίου πρόσβασης που επιλέγει, σύμφωνα με οδηγίες της αρμόδιας αρχής και χορηγείται από την Υπηρεσία Εξετάσεων,\n(β) για τα ΑΑΕΙ της Ελλάδας, το βαθμό που εξάγεται σε εικοσάβαθμη κλίμακα, ο οποίος προκύπτει από τη γραπτή ή και άλλης μορφής αξιολόγηση του υποψηφίου στα εξεταζόμενα μαθήματα του πλαισίου πρόσβασης που επιλέγει, σύμφωνα με οδηγίες της αρμόδιας αρχής κατόπιν συνεννόησης με το Υπουργείο Παιδείας, Έρευνας και Θρησκευμάτων της Ελλάδας.\n«δελτίο υποψηφίου» σημαίνει την έντυπη ή την ηλεκτρονική επιστολή, η οποία αποστέλλεται από την Υπηρεσία Εξετάσεων προς τον υποψήφιο, με την οποία ενημερώνεται για τον αριθμό υποψηφίου και για τα εξεταστικά κέντρα στα οποία θα εξεταστεί.\n«Δημόσια Ανώτερα και Ανώτατα Εκπαιδευτικά Ιδρύματα της Κύπρου» ή «ΑΑΕΙ της Κύπρου» ως Ανώτατα σημαίνει το Πανεπιστήμιο Κύπρου και το Τεχνολογικό Πανεπιστήμιο Κύπρου και ως Ανώτερα το Ανώτερο Ξενοδοχειακό Ινστιτούτο Κύπρου, καθώς επίσης και οποιαδήποτε άλλα Ιδρύματα Ανώτατης και Ανώτερης Εκπαίδευσης ορίσει η αρμόδια αρχή.\n«δημόσιο σχολείο Μέσης Εκπαίδευσης» έχει την έννοια που αποδίδεται στον όρο αυτό από το άρθρο 2 του περί Δημόσιας Εκπαιδευτικής Υπηρεσίας Νόμου.\n«δολίευση» σημαίνει κάθε προσπάθεια που γίνεται από υποψήφιο για να ολοκληρώσει το εξεταστικό του δοκίμιο με δόλια μέσα, όπως η αντιγραφή από συνυποψήφιό του ή η κατοχή ή/και χρήση μη επιτρεπόμενων βοηθημάτων/σημειώσεων ή ηλεκτρονικών συσκευών στις οποίες αποθηκεύονται πληροφορίες και μεταφέρονται παράνομα στο εξεταστικό κέντρο ή η χρησιμοποίηση μέρους ή ολόκληρου του γραπτού άλλου υποψηφίου ως δικού του ή η αποδοχή ή/και παροχή βοήθειας από άλλους εξεταζομένους ή άλλο πρόσωπο ή η γνώση εκ των προτέρων των θεμάτων της εξέτασης ή η με οποιοδήποτε άλλο τρόπο απόπειρα εξαπάτησης με στόχο την επιτυχία στις εξετάσεις.\n«Ειδική Επιτροπή Παροχής Διευκολύνσεων» σημαίνει την Ειδική Επιτροπή που ορίζεται από την αρμόδια αρχή, σύμφωνα με τις διατάξεις του άρθρου 11, για την εξέταση των αιτήσεων των υποψηφίων με ειδικές ανάγκες και την παροχή των αναγκαίων διευκολύνσεων κατά τη διεξαγωγή των Παγκύπριων Εξετάσεων Πρόσβασης.\n«εξεταστικό κέντρο» σημαίνει το κέντρο που ορίζεται από την Υπηρεσία Εξετάσεων, σε συνεργασία με τις Διευθύνσεις Μέσης Εκπαίδευσης του Υπουργείου Παιδείας και Πολιτισμού, για τη διεξαγωγή των Παγκύπριων Εξετάσεων Πρόσβασης.\n«επιτηρητής» σημαίνει τον εκπαιδευτικό που είναι εντεταλμένος για την επιτήρηση της ομαλής και αδιάβλητης διεξαγωγής των Παγκύπριων Εξετάσεων Πρόσβασης.\n«Επιτροπή Εξεταστικού Κέντρου» σημαίνει την επιτροπή που ορίζεται από τη διεύθυνση του σχολείου που λειτουργεί ως εξεταστικό κέντρο, η οποία αναλαμβάνει τη διεκπεραίωση όλων των απαραίτητων διαδικασιών που σχετίζονται με τη διενέργεια και ολοκλήρωση των Παγκύπριων Εξετάσεων Πρόσβασης στα εξεταστικά κέντρα, συμπεριλαμβανομένης της διαδικασίας παραλαβής των εξεταστικών δοκιμίων από το συντονιστικό κέντρο της επαρχίας και της παράδοσης των τετραδίων απαντήσεων των υποψηφίων στο συντονιστικό κέντρο της επαρχίας στην οποία ανήκει το κέντρο.\n«Επιτροπή Θεματοθέτησης» σημαίνει την πενταμελή επιτροπή θεματοθετών που έχει ως όρους εντολής την ετοιμασία θεμάτων για κάθε μέρος του εξεταστικού δοκιμίου, όπως και την κατάρτιση του εξεταστικού δοκιμίου, σύμφωνα με τις οδηγίες της αρμόδιας αρχής, τα οποία υποβάλλουν για έλεγχο στην Επιτροπή Ελέγχου.\n«Επιτροπή Παγκύπριων Εξετάσεων Πρόσβασης» ή άλλως «ΕΠΕΠ» σημαίνει την επιτροπή, η οποία έχει την ευθύνη της τελικής επιλογής των θεματοθετών, καθώς και την ευθύνη της επιλογής των βαθμολογητών των Παγκύπριων Εξετάσεων Πρόσβασης.\n«θεματοθέτης» σημαίνει τον εκπαιδευτικό που διορίζεται ως μέλος της Επιτροπής Θεματοθέτησης και έχει την ευθύνη μαζί με τα υπόλοιπα μέλη της επιτροπής για την ετοιμασία εξεταστικού δοκιμίου συγκεκριμένου μαθήματος που περιλαμβάνεται στα πλαίσια πρόσβασης.\n«θέση» σημαίνει τη διαθέσιμη θέση στα ΑΑΕΙ της Κύπρου, την οποία διεκδικούν οι υποψήφιοι των Παγκύπριων Εξετάσεων Πρόσβασης.\n«ιδιωτικό σχολείο Μέσης Εκπαίδευσης» έχει την έννοια που αποδίδεται στον όρο αυτό από τον περί Ιδιωτικών Σχολείων και Φροντιστηρίων Νόμο.\n«κέντρο βαθμολόγησης» σημαίνει το κέντρο, το οποίο ορίζεται από την Υπηρεσία Εξετάσεων για τη διεκπεραίωση της διαδικασίας βαθμολόγησης των τετραδίων απαντήσεων των υποψηφίων.\n«λυκειακός κύκλος» έχει την έννοια που αποδίδεται στον όρο αυτό από τους περί Λειτουργίας των Δημόσιων Σχολείων Μέσης Εκπαίδευσης Κανονισμούς.\n«μέλος Επιτροπής Εξεταστικού Κέντρου» σημαίνει τον εκπαιδευτικό που ορίζεται από τη Διεύθυνση του Σχολείου Μέσης Εκπαίδευσης που λειτουργεί ως εξεταστικό κέντρο, σύμφωνα με τους κανόνες και τις οδηγίες της Υπηρεσίας Εξετάσεων.\n«οδηγός διόρθωσης» σημαίνει τις γραπτές οδηγίες που δίνονται από τους θεματοθέτες προς τους βαθμολογητές, οι οποίες δύναται να διαμορφώνονται μετά το συντονισμό βαθμολόγησης και αφορούν τον τρόπο βαθμολόγησης των γραπτών απαντήσεων.\n«Οδηγός Παγκύπριων Εξετάσεων Πρόσβασης» σημαίνει το έντυπο ή το ηλεκτρονικό αρχείο που εκδίδει ή αναρτά στην ιστοσελίδα της η Υπηρεσία Εξετάσεων, σύμφωνα με τις διατάξεις του άρθρου 30, κατόπιν έγκρισης της αρμόδιας αρχής.\n«πίνακας προδιαγραφών» σημαίνει τον πίνακα που περιέχει τις παραμέτρους και προδιαγραφές, βάσει των οποίων καταρτίζεται το εξεταστικό δοκίμιο κάθε εξεταζόμενου μαθήματος.\n«πιστοποιητικό πρόσβασης» σημαίνει τη βεβαίωση που χορηγεί σε κάθε ενδιαφερόμενο υποψήφιο η Υπηρεσία Εξετάσεων, στην οποία αναγράφεται το Τμήμα/Σχολή επιτυχίας του υποψηφίου στα Δημόσια ΑΑΕΙ της Κύπρου, σε περίπτωση που έχει επιτύχει και επιθυμεί πρόσβαση στα ΑΑΕΙ της Κύπρου, καθώς και οι αρχικές βαθμολογίες που εξασφάλισε ο υποψήφιος, όπως και οι βαθμοί κατάταξης ανά πλαίσιο πρόσβασης.\n«πλαίσιο πρόσβασης» σημαίνει την ομάδα μαθημάτων που ορίζεται από την αρμόδια αρχή ανά Τμήμα/Σχολή Τριτοβάθμιας Εκπαίδευσης, τα οποία αποτελούν τα εξεταζόμενα μαθήματα στις Παγκύπριες Εξετάσεις Πρόσβασης, για σκοπούς εισαγωγής στα Δημόσια ΑΑΕΙ της Κύπρου.\n«πρακτική δοκιμασία» σημαίνει το εξεταζόμενο μάθημα πρόσβασης κατά το οποίο ο υποψήφιος εξετάζεται σε αθλητικές δοκιμασίες, όπως καθορίζονται στο Παράρτημα Ι, οι οποίες βαθμολογούνται από την οριζόμενη Αγωνόδικο Επιτροπή.\n«πρόεδρος Επιτροπής Εξεταστικού Κέντρου» σημαίνει τον εκπαιδευτικό που ορίζεται από τη διεύθυνση του σχολείου Μέσης Εκπαίδευσης που λειτουργεί ως εξεταστικό κέντρο και έχει τη γενική ευθύνη της ομαλής λειτουργίας του συγκεκριμένου εξεταστικού κέντρου κατά τη διεξαγωγή των Παγκύπριων Εξετάσεων Πρόσβασης, σύμφωνα με τους κανόνες και τις οδηγίες της Υπηρεσίας Εξετάσεων.\n«Υπεύθυνη Δήλωση» σημαίνει τη δήλωση, το περιεχόμενο της οποίας καθορίζεται στο Παράρτημα ΙΙΙ.\n«Υπηρεσία Εξετάσεων» σημαίνει την υπηρεσία του Υπουργείου Παιδείας και Πολιτισμού, η οποία έχει την ευθύνη για την προετοιμασία, διεξαγωγή και εξαγωγή των αποτελεσμάτων των Παγκύπριων Εξετάσεων Πρόσβασης.\n«υποψήφιος» σημαίνει το πρόσωπο που συμμετέχει στις Παγκύπριες Εξετάσεις Πρόσβασης, για σκοπούς εξασφάλισης του πιστοποιητικού πρόσβασης και του βαθμού κατάταξης, καθώς και στη διαδικασία της κατανομής των θέσεων στα Δημόσια ΑΑΕΙ της Κύπρου ή/και της Ελλάδας.\n«υποψήφιος με ειδικές ανάγκες» σημαίνει τον υποψήφιο που σύμφωνα με τις διατάξεις του περί Αγωγής και Εκπαίδευσης Παιδιών με Ειδικές Ανάγκες Νόμου, έχει σοβαρή μαθησιακή ή ειδική μαθησιακή, λειτουργική και προσαρμοστική, δυσκολία που οφείλεται σε σωματικές, συμπεριλαμβανομένων των αισθητηριακών, διανοητικές ή άλλες γνωστικές ή ψυχικές ανεπάρκειες ή άλλου είδους εκ γενετής ή επίκτητες δυσχέρειες που χρήζουν ειδικής/ων διευκόλυνσης/σεων, για σκοπούς συμμετοχής στις Παγκύπριες Εξετάσεις Πρόσβασης."
    },
    {
      "provision_ref": "sec3",
      "section": "3",
      "title": "Άρθρο 3: Υπηρεσία Εξετάσεων",
      "content": "3. Τηρουμένων των διατάξεων του παρόντος Νόμου, του Οδηγού Παγκύπριων Εξετάσεων Πρόσβασης και σύμφωνα με τις οδηγίες της αρμόδιας αρχής, η Υπηρεσία Εξετάσεων έχει την ευθύνη της οργάνωσης, διεξαγωγής και εξαγωγής των αποτελεσμάτων των Παγκύπριων Εξετάσεων Πρόσβασης, καθώς και την ευθύνη της κατανομής των θέσεων στα Δημόσια ΑΑΕΙ της Κύπρου."
    },
    {
      "provision_ref": "sec4",
      "section": "4",
      "title": "Άρθρο 4: Σκοπός των Παγκύπριων Εξετάσεων Πρόσβασης",
      "content": "4. Ο σκοπός των Παγκύπριων Εξετάσεων Πρόσβασης είναι-\n(α) Η χορήγηση του βαθμού κατάταξης ανά πλαίσιο πρόσβασης και του πιστοποιητικού πρόσβασης στους υποψηφίους.\n(β) η κατανομή των θέσεων στα Δημόσια ΑΑΕΙ της Κύπρου.\n(γ) η προώθηση της βάσης δεδομένων με τους βαθμούς κατάταξης και τις δηλώσεις προτίμησης των υποψηφίων στο Υπουργείο Παιδείας, Έρευνας και Θρησκευμάτων της Ελλάδας για την κατανομή των θέσεων στα Δημόσια ΑΑΕΙ της Ελλάδας:\nΝοείται ότι, το πιστοποιητικό πρόσβασης και ο βαθμός κατάταξης ισχύουν μόνο για το έτος διεξαγωγής των Παγκύπριων Εξετάσεων Πρόσβασης, στη βάση των οποίων χορηγούνται τα πιο πάνω."
    },
    {
      "provision_ref": "sec5",
      "section": "5",
      "title": "Άρθρο 5: Διεξαγωγή Παγκύπριων Εξετάσεων Πρόσβασης",
      "content": "5.-(1) Η ημερομηνία έναρξης των Παγκύπριων Εξετάσεων Πρόσβασης τοποθετείται αμέσως μετά την ολοκλήρωση των Παγκύπριων Εξετάσεων Απόλυσης για την Γʹ τάξη Λυκείου.\n(2) Η ολοκλήρωση των εξεταζόμενων μαθημάτων των Παγκύπριων Εξετάσεων Πρόσβασης τοποθετείται μέχρι τα τέλη Ιουνίου."
    },
    {
      "provision_ref": "sec6",
      "section": "6",
      "title": "Άρθρο 6: Δικαίωμα συμμετοχής στις Παγκύπριες Εξετάσεις Πρόσβασης",
      "content": "6. Δικαίωμα συμμετοχής στις Παγκύπριες Εξετάσεις Πρόσβασης για εισαγωγή στα Δημόσια ΑΑΕΙ της Κύπρου έχουν-\n(α) Οι Κύπριοι υπήκοοι ή όσοι έχουν έναν από τους γονείς τους κυπριακής καταγωγής και οι οποίοι είναι-\n(i) μαθητές της τελευταίας τάξης ή απόφοιτοι λυκειακού κύκλου δημόσιων σχολείων Μέσης Εκπαίδευσης ή της Αγγλικής Σχολής Λευκωσίας, που λειτουργεί σύμφωνα με τις διατάξεις του περί Αγγλικής Σχολής (Διεύθυνση και Έλεγχος) Νόμου ή των ιδιωτικών σχολείων που ιδρύθηκαν και λειτουργούν σύμφωνα με τις διατάξεις του περί Ιδιωτικών Σχολείων και Φροντιστηρίων Νόμου.\n(ii) μαθητές της τελευταίας τάξης ή απόφοιτοι σχολείου ανώτερης δευτεροβάθμιας εκπαίδευσης, λυκειακού επιπέδου, που λειτουργεί νόμιμα σε ξένη χώρα, με την προϋπόθεση ότι προσκομίζουν πιστοποιητικό της αρμόδιας εκπαιδευτικής ή διπλωματικής αρχής της χώρας αυτής που βεβαιώνει ότι το συγκεκριμένο απολυτήριο, που κατέχει ή πρόκειται να αποκτήσει ο υποψήφιος, του παρέχει το δικαίωμα εισαγωγής στα αντίστοιχα Ιδρύματα Ανώτερης και Ανώτατης Εκπαίδευσης της χώρας αυτής. και\n(β) υπήκοοι της Ευρωπαϊκής Ένωσης και υπήκοοι τρίτων χωρών, οι οποίοι φοιτούν στην τελευταία τάξη ή είναι απόφοιτοι σχολείου όπως περιγράφεται στην υποπαράγραφο (i) της παραγράφου (α):\nΝοείται ότι, οι μαθητές της τελευταίας τάξης που σημείωσαν αριθμό απουσιών μεγαλύτερο των εκατόν τριάντα πέντε (135), του αριθμού αυτού περιλαμβανόμενου, και παραμένουν στάσιμοι όπως προβλέπεται στους περί Λειτουργίας των Δημόσιων Σχολείων Μέσης Εκπαίδευσης Κανονισμούς, δεν έχουν δικαίωμα συμμετοχής στις Παγκύπριες Εξετάσεις Πρόσβασης."
    },
    {
      "provision_ref": "sec7",
      "section": "7",
      "title": "Άρθρο 7: Τέλη Παγκύπριων Εξετάσεων Πρόσβασης",
      "content": "7.-(1) Οι υποψήφιοι καταβάλλουν τέλη, για να λάβουν μέρος στις Παγκύπριες Εξετάσεις Πρόσβασης.\n(2) (α) Το ύψος των τελών, που αναφέρονται στο εδάφιο (1), για κάθε μάθημα καθορίζεται και αναθεωρειται, σύμφωνα με τις διατάξεις του άρθρου 39 του περί της Λογιστικής και Δημοσιονομικής Διαχείρισης και Χρηματοοικονομικού Ελέγχου της Δημοκρατίας Νόμου και αναγράφονται στον Οδηγό Παγκύπριων Εξετάσεων Πρόσβασης.\n(β) Τα τέλη καταβάλλονται με την υποβολή της αίτησης ή σε ειδικές περιπτώσεις, σε μεταγενέστερο στάδιο, με την έγκριση της αρμόδιας αρχής και σχετικής ανακοίνωσης στον Οδηγό Παγκύπριων Εξετάσεων Πρόσβασης.\n(γ) Τα τέλη δεν επιστρέφονται στους υποψήφιους σε περίπτωση απόσυρσης, τροποποίησης ή μη επαναϋποβολής της αίτησης."
    },
    {
      "provision_ref": "sec8",
      "section": "8",
      "title": "Άρθρο 8: Αιτήσεις για συμμετοχή στις Παγκύπριες Εξετάσεις Πρόσβασης",
      "content": "8.- (1)(α) Η Υπηρεσία Εξετάσεων ανακοινώνει έγκαιρα στον Οδηγό Παγκύπριων Εξετάσεων Πρόσβασης ή/και στην επίσημη ιστοσελίδα της ή/και στον ημερήσιο τύπο, τη διαδικασία υποβολής των αιτήσεων, όπως και τις προθεσμίες υποβολής των αιτήσεων για συμμετοχή στις Παγκύπριες Εξετάσεις Πρόσβασης.\n(β) Δεν επιτρέπεται η υποβολή αίτησης συμμετοχής στις Παγκύπριες Εξετάσεις Πρόσβασης, σε χρονική περίοδο εκτός των οριζόμενων από την Υπηρεσία Εξετάσεων χρονοδιαγραμμάτων, στα οποία περιλαμβάνεται και προκαθορισμένη παράταση του χρόνου υποβολής των αιτήσεων για υποψηφίους που θα παρουσιάσουν τεκμηριωμένα σοβαρούς λόγους.\n(2) (α) Η αίτηση κάθε ενδιαφερόμενου υποψηφίου συνοδεύεται από τα αποδεικτικά στοιχεία που απαιτούνται για την εγκυρότητά της, όπως αυτά καθορίζονται στον Οδηγό Παγκύπριων Εξετάσεων Πρόσβασης.\n(β) Η ευθύνη για τη συμπλήρωση της αίτησης όσον αφορά τα προσωπικά στοιχεία, τις επιλογές των προτεινόμενων από τον αιτητή Τμημάτων/Σχολών των ΑΑΕΙ, ανήκει αποκλειστικά στον αιτητή."
    },
    {
      "provision_ref": "sec9",
      "section": "9",
      "title": "Άρθρο 9: Αίτηση συμμετοχής και δήλωση προτίμησης υποψηφίων στις Παγκύπριες Εξετάσεις Πρόσβασης",
      "content": "9.-(1) Με τη συμπλήρωση της αίτησης συμμετοχής στις Παγκύπριες Εξετάσεις Πρόσβασης, ο ενδιαφερόμενος υποψήφιος δηλώνει τη σειρά προτίμησής του για τα Τμήματα/Σχολές στα οποία επιθυμεί να είναι υποψήφιος.\n(2) Με τη δήλωση προτίμησης, ο ενδιαφερόμενος υποψήφιος αποδέχεται ότι-\n(α) Δεν μπορεί να εξασφαλίσει θέση σε Τμήμα/Σχολή που δεν έχει συμπεριλάβει στις προτιμήσεις του.\n(β) δεν μπορεί να εξασφαλίσει θέση σε Τμήμα/Σχολή στο/στην οποίο/α τις θέσεις καταλαμβάνουν υποψήφιοι με ψηλότερη βαθμολογία.\n(γ) θα του δοθεί θέση μόνο σε εκείνο το Τμήμα/Σχολή που προσδιόρισε στη δήλωσή του με ένδειξη προτίμησης ψηλότερης προτεραιότητας σε σχέση με άλλα Τμήματα/Σχολές που έχει δηλώσει, σε περίπτωση κατά την οποία, σύμφωνα με τους βαθμούς κατάταξης που θα πάρει στα διάφορα πλαίσια πρόσβασης στα οποία επιθυμεί να εξεταστεί, μπορεί να εξασφαλίσει θέση σε περισσότερα από ένα Τμήματα/Σχολές. για τους σκοπούς της παρούσας παραγράφου, ψηλότερης προτεραιότητας προτίμηση είναι το Τμήμα/Σχολή που δηλώθηκε στη θέση με αριθμό 1 και η αμέσως χαμηλότερης προτεραιότητας προτίμηση είναι το Τμήμα/Σχολή που δηλώθηκε στη θέση με αριθμό 2 και ούτω καθεξής.\n(δ) δηλώνει τη σειρά προτίμησής του κατά τρόπο ενιαίο για τα Τμήματα/Σχολές στα/στις οποία/ες επιθυμεί να είναι υποψήφιος και όχι για κάθε πλαίσιο πρόσβασης ξεχωριστά. με βάση τη δήλωσή του μπορεί η πρώτη προτίμησή του να είναι Τμήμα/Σχολή το/η οποίο/α ανήκει σε ένα πλαίσιο πρόσβασης, το/η δεύτερο/η σε άλλο πλαίσιο πρόσβασης και ούτω καθεξής.\n(3)(α) Κάθε υποψήφιος πρέπει να υποβάλει την αίτησή του εντός της καθορισμένης προθεσμίας, όπως δημοσιεύεται στον Οδηγό Παγκύπριων Εξετάσεων Πρόσβασης.\n(β) Τροποποίηση της αίτησης υποψηφίου μπορεί να γίνει μόνο εντός της καθορισμένης από την Υπηρεσία Εξετάσεων προθεσμίας, που δημοσιεύεται στον Οδηγό των Παγκύπριων Εξετάσεων Πρόσβασης:\nΝοείται ότι, σε περίπτωση επιλογής πρόσθετων μαθημάτων κατά την τροποποίηση της αίτησής του, ο αιτητής καταβάλλει τα πρόσθετα τέλη."
    },
    {
      "provision_ref": "sec10",
      "section": "10",
      "title": "Άρθρο 10: Υποβολή αίτησης υποψηφίων με ειδικές ανάγκες για παροχή διευκολύνσεων",
      "content": "10. Οι υποψήφιοι με ειδικές ανάγκες υποβάλλουν, μαζί με την αίτηση για συμμετοχή στις Παγκύπριες Εξετάσεις Πρόσβασης, αίτηση, με τα αναγκαία δικαιολογητικά προς την Υπηρεσία Εξετάσεων, για παροχή σε αυτούς διευκολύνσεων κατά τη διαδικασία διεξαγωγής των Παγκύπριων Εξετάσεων Πρόσβασης και για έκδοση της σχετικής απόφασης που αναφέρεται στο εδάφιο (4) του άρθρου 11 του παρόντος Νόμου."
    },
    {
      "provision_ref": "sec11",
      "section": "11",
      "title": "Άρθρο 11: Ειδική Επιτροπή για Παροχή Διευκολύνσεων",
      "content": "11.-(1) Η αρμόδια αρχή ορίζει έκαστο έτος Ειδική Επιτροπή Παροχής Διευκολύνσεων για υποψηφίους με ειδικές ανάγκες.\n(2) Η Ειδική Επιτροπή Παροχής Διευκολύνσεων απαρτίζεται από-\n(α) Την/τον Προϊστάμενη/ο της Υπηρεσίας Εξετάσεων, ως Πρόεδρο,\n(β) ένα εκπρόσωπο της Υπηρεσίας Ειδικής Αγωγής και Εκπαίδευσης του Υπουργείου Παιδείας και Πολιτισμού,\n(γ) ένα εκπρόσωπο της Υπηρεσίας Εκπαιδευτικής Ψυχολογίας του Υπουργείου Παιδείας και Πολιτισμού, και\n(δ) ένα εκπρόσωπο της Υπηρεσίας Συμβουλευτικής και Επαγγελματικής Αγωγής του Υπουργείου Παιδείας και Πολιτισμού.\n(3) Η παροχή των διευκολύνσεων, που αναφέρονται στο εδάφιο (1)-\n(α) Στοχεύει στη διασφάλιση των θεσμοθετημένων δικαιωμάτων των ατόμων με ειδικές ανάγκες, κατά τη διάρκεια των Παγκύπριων Εξετάσεων Πρόσβασης, ως αντιστάθμισμα της αναπηρίας ή του ειδικού προβλήματος που αντιμετωπίζουν.\n(β) διαφυλάσσει το αδιάβλητο των Παγκύπριων Εξετάσεων Πρόσβασης. και\n(γ) δεν δίνει προβάδισμα σε οποιοδήποτε υποψήφιο ή ομάδα υποψηφίων.\n(4) Η Ειδική Επιτροπή Παροχής Διευκολύνσεων εξετάζει την κάθε αίτηση που υποβάλλεται από τον υποψήφιο με ειδικές ανάγκες, για παροχή διευκολύνσεων, λαμβάνοντας υπόψη τις διευκολύνσεις που ζητά ο υποψήφιος, τους λόγους που επικαλείται και τα πιστοποιητικά και/ή δικαιολογητικά που συνοδεύουν και υποστηρίζουν την αίτησή του και εκδίδει προς τούτο σχετική απόφαση.\n(5) Η Ειδική Επιτροπή Παροχής Διευκολύνσεων, κατά τη μελέτη αίτησης για παροχή διευκολύνσεων, καλεί εκπαιδευτικούς ή άλλους ειδικούς στο θέμα της ειδικής ανάγκης που αντιμετωπίζει ο υποψήφιος με ειδικές ανάγκες, οι οποίοι θα τη βοηθούν στην αξιολόγηση της κάθε αίτησης."
    },
    {
      "provision_ref": "sec12",
      "section": "12",
      "title": "Άρθρο 12: Καθορισμός εξεταστέας ύλης και θέματα εξέτασης",
      "content": "12.–(1) Η εξεταστέα ύλη για κάθε μάθημα καθορίζεται από την αρμόδια αρχή και δημοσιεύεται στον Οδηγό Παγκύπριων Εξετάσεων Πρόσβασης.\n(2) Με ευθύνη των Διευθύνσεων Μέσης Εκπαίδευσης, καταρτίζεται και παραδίδεται στον/στην Προϊστάμενο/η της Υπηρεσίας Εξετάσεων λεπτομερής πίνακας προδιαγραφών για κάθε εξεταστικό δοκίμιο των Παγκύπριων Εξετάσεων Πρόσβασης, ο οποίος κοινοποιείται στους υποψηφίους το μήνα Νοέμβριο κάθε σχολικού έτους, μέσω της ιστοσελίδας της Υπηρεσίας Εξετάσεων και μέσω του Οδηγού Παγκύπριων Εξετάσεων Πρόσβασης."
    },
    {
      "provision_ref": "sec13",
      "section": "13",
      "title": "Άρθρο 13: Σύσταση Επιτροπής Παγκύπριων Εξετάσεων Πρόσβασης (ΕΠΕΠ) για ορισμό επιτροπών θεματοθετών",
      "content": "13. Για τους σκοπούς της τελικής επιλογής των επιτροπών θεματοθετών κάθε εξεταζόμενου μαθήματος συστήνεται τριμελής Επιτροπή Παγκύπριων Εξετάσεων Πρόσβασης (ΕΠΕΠ), της οποίας προεδρεύει η/ο Προϊστάμενη/ος της Υπηρεσίας Εξετάσεων και συμμετέχουν οι Διευθυντές Μέσης Γενικής (ΔΜΕ) και Μέσης Τεχνικής και Επαγγελματικής Εκπαίδευσης (ΔΜΤΕΕ), ανάλογα με το μάθημα εξέτασης, και ένας Επιθεωρητής του υπό εξέταση μαθήματος, άλλου ή συναφούς μαθήματος. σε περίπτωση που δεν υπάρχει επαρκής αριθμός κατάλληλων θεματοθετών σύμφωνα με τα καθορισμένα στον παρόντα Νόμο κριτήρια, η τριμελής ΕΠΕΠ ορίζει θεματοθέτες."
    },
    {
      "provision_ref": "sec14",
      "section": "14",
      "title": "Άρθρο 14: Επιτροπή Θεματοθέτησης",
      "content": "14.- (1) Για κάθε εξεταζόμενο μάθημα συστήνεται Επιτροπή Θεματοθέτησης.\n(2) Οι υποψήφιοι θεματοθέτες είναι υποχρεωμένοι να παρακολουθούν εκ των προτέρων ειδικά επιμορφωτικά σεμινάρια σε θέματα αξιολόγησης, όπως και σε θέματα παροχής διευκολύνσεων σε υποψήφιους με ειδικές ανάγκες, τα οποία διοργανώνει η Υπηρεσία Εξετάσεων, σε συνεργασία με τις Διευθύνσεις Μέσης Εκπαίδευσης και το Παιδαγωγικό Ινστιτούτο Κύπρου. για σκοπούς επιμόρφωσης, όπου είναι δυνατό, καλείται ο διπλάσιος αριθμός θεματοθετών από τον προβλεπόμενο αριθμό με βάση τις διατάξεις του άρθρου 16.\n(3) Η/Ο Προϊστάμενη/ος της Υπηρεσίας Εξετάσεων υποβάλλει στην αρμόδια αρχή για έγκριση τα μέλη κάθε Επιτροπής Θεματοθετών, τα οποία ειδοποιούνται για την εργασία τους την παραμονή της ημέρας που αναλαμβάνουν καθήκον.\n(4) (α) Η Επιτροπή Θεματοθέτησης προβαίνει σε όλες τις αναγκαίες ενέργειες, για να αποφευχθούν τυχόν λάθη και ελλείψεις ή ασάφειες στα θέματα, ώστε να διασφαλίζεται ότι αυτά έχουν το μεγαλύτερο δυνατό βαθμό εγκυρότητας και αξιοπιστίας, ότι αυτά καλύπτουν διαφορετικά επίπεδα δυσκολίας, ώστε να παρέχεται δυνατότητα διάκρισης των υποψηφίων, ότι αυτά περιλαμβάνονται στην εξεταστέα ύλη, σύμφωνα με τον Οδηγό Παγκύπριων Εξετάσεων Πρόσβασης, και ότι μπορούν να απαντηθούν στο χρόνο που διατίθεται για την εξέταση.\n(β) Η Επιτροπή Θεματοθέτησης οφείλει να λαμβάνει υπόψη τις διευκολύνσεις που έχουν παραχωρηθεί από την Ειδική Επιτροπή Παροχής Διευκολύνσεων σε υποψήφιους με ειδικές ανάγκες."
    },
    {
      "provision_ref": "sec15",
      "section": "15",
      "title": "Άρθρο 15: Κριτήρια επιλογής των θεματοθετών",
      "content": "15.- (1) Τα κριτήρια επιλογής των θεματοθετών είναι-\n(α) Να έχουν μονιμότητα και αναγνωρισμένη από την Επιτροπή Εκπαιδευτικής Υπηρεσίας υπηρεσία τουλάχιστον οκτώ (8) ετών.\n(β) να έχουν διδάξει το υπό εξέταση μάθημα για τουλάχιστον πέντε (5) έτη στην Γ΄ τάξη Λυκείου ή Γ΄ τάξη Τεχνικών Σχολών, εκ των οποίων το ένα να είναι η τρέχουσα ή η προηγούμενη από την εξέταση σχολική χρονιά.\n(γ) να μην παραδίδουν φροντιστηριακά μαθήματα και να μην διδάσκουν μαθήματα των Παγκύπριων Εξετάσεων Πρόσβασης στα Κρατικά Ινστιτούτα Επιμόρφωσης (Κ.Ι.Ε.), στα βραδινά τμήματα των Τεχνικών Σχολών ή αλλού, να μην είναι ιδιοκτήτες Φροντιστηρίου και να μην έχουν άμεση ή έμμεση σχέση με ιδιοκτήτη/τρια Φροντιστηρίου.\n(δ) να μην αναλαμβάνουν καθήκοντα θεματοθέτησης, όπου είναι δυνατό, σε περισσότερα από δύο μαθήματα.\n(ε) να συμμετέχουν σε υποχρεωτικά σεμινάρια επιμόρφωσης που οργανώνονται εκ των προτέρων για το σκοπό αυτό από την Υπηρεσία Εξετάσεων, τις Διευθύνσεις Μέσης Εκπαίδευσης και το Παιδαγωγικό Ινστιτούτο Κύπρου.\n(2) (α) Η κατοχή μεταπτυχιακού τίτλου στο υπό εξέταση μάθημα ή στον τομέα της εκπαιδευτικής αξιολόγησης ή στον τομέα των παιδαγωγικών με συνάφεια στο υπό εξέταση μάθημα, θεωρείται πρόσθετο προσόν.\n(β) Επαρκής εμπειρία στη θεματοθέτηση, δύναται να λαμβάνεται υπόψη."
    },
    {
      "provision_ref": "sec16",
      "section": "16",
      "title": "Άρθρο 16: Σύνθεση Επιτροπής Θεματοθέτησης",
      "content": "16. (1)(α) Στην Επιτροπή Θεματοθέτησης συμμετέχουν-\n(i) Ένας Επιθεωρητής Μέσης Εκπαίδευσης ή ΒΔ Α΄ ή ΒΔ, όλοι της ειδικότητας του υπό εξέταση μαθήματος ή άλλης συναφούς ειδικότητας μαθήματος,\n(ii) τρεις έμπειροι καθηγητές ή ΒΔΑ’ ή ΒΔ΄ Δημόσιων Σχολείων Μέσης Εκπαίδευσης, οι οποίοι έχουν διδάξει το υπό εξέταση μάθημα τουλάχιστον για πέντε χρόνια, εκ των οποίων το ένα να είναι η τρέχουσα ή η προηγούμενη από την εξέταση σχολική χρονιά, και,\n(iii) όπου είναι δυνατό, ένα μέλος του διδακτικού προσωπικού των Δημόσιων ΑΑΕΙ της Κύπρου:\nΝοείται ότι όπου δεν είναι δυνατό να συμμετέχει μέλος του διδακτικού προσωπικού των Δημόσιων ΑΑΕΙ, αυξάνεται κατά ένα (1) ο αριθμός των καθηγητών ή ΒΔ Α΄ ή ΒΔ Μέσης Εκπαίδευσης.\n(β) Για σκοπούς διασφάλισης της συμμετοχής όσο το δυνατό διαφορετικών θεματοθετών στις Επιτροπές Θεματοθέτησης, η αρμόδια αρχή λειτουργεί με βάση τις αρχές της εναλλαξιμότητας.\n(2) Η Επιτροπή Θεματοθέτησης συνέρχεται εικοσιτέσσερις (24) έως σαράντα οκτώ (48) ώρες πριν την καθορισμένη ημέρα και ώρα της εξέτασης του κάθε μαθήματος, σε χώρο και σε ακριβή χρόνο που καθορίζονται από την αρμόδια αρχή, με γνώμονα την πλήρη διασφάλιση του αδιάβλητου των Παγκύπριων Εξετάσεων Πρόσβασης.\n(3) Τα μέλη της Επιτροπής Θεματοθέτησης υπογράφουν Υπεύθυνη Δήλωση, όπως αυτή καθορίζεται στο Παράρτημα ΙΙΙ.\n(4) Οι όροι εντολής της Επιτροπής Θεματοθέτησης καθορίζονται με βάση τον πίνακα προδιαγραφών και τις ανάγκες του κάθε μαθήματος και δίδονται από τον πρόεδρο κάθε Επιτροπής Θεματοθέτησης σε κάθε μέλος χωριστά. κάθε μέλος της Επιτροπής Θεματοθέτησης ετοιμάζει, κάτω από συνθήκες απόλυτης εχεμύθειας και εμπιστευτικότητας, ένα θέμα για δύο διαφορετικά μέρη του εξεταστικού δοκιμίου, ώστε να διασφαλίζεται ότι θα υπάρχουν δύο θέματα, για κάθε μέρος του εξεταστικού δοκιμίου.\n(5) (α) Τα θέματα των εξεταστικών δοκιμίων των Παγκύπριων Εξετάσεων Πρόσβασης εξυπηρετούν το συγκριτικό σκοπό αξιολόγησης, είναι κλιμακούμενης δυσκολίας και υψηλού δείκτη διάκρισης.\n(β) Τα μέλη της Επιτροπής Θεματοθέτησης ολοκληρώνουν την ετοιμασία των θεμάτων που τους ανατίθενται και παράλληλα καταγράφουν την εκτίμησή τους για το βαθμό δυσκολίας των θεμάτων τους και ετοιμάζουν Οδηγό Διόρθωσης, που περιλαμβάνει τη λύση ή τις λύσεις και τον τρόπο βαθμολόγησης.\n(6)(α) Η Επιτροπή Θεματοθέτησης συνέρχεται σε ολομέλεια και εξετάζει ένα προς ένα όλα τα θέματα που έχουν ετοιμαστεί, με σκοπό τον καταρτισμό του ολοκληρωμένου εξεταστικού δοκιμίουκαι τον λεπτομερή έλεγχό του.\n(β) Η Επιτροπή Θεματοθέτησης φροντίζει για τη διασφάλιση της ορθότητας, της εγκυρότητας, της αξιοπιστίας, του κατάλληλου βαθμού δυσκολίας και διάκρισης, της συμφωνίας των θεμάτων του εξεταστικού δοκιμίου με την υπό εξέταση ύλη και με τον πίνακα προδιαγραφών, καθώς και με άλλους όρους που αναφέρονται στον παρόντα Νόμο και στον Οδηγό Παγκύπριων Εξετάσεων Πρόσβασης.\n(γ) Τα μέλη της Επιτροπής Θεματοθέτησης παραμένουν στο χώρο της θεματοθέτησης και δεν αποχωρούν από το χώρο αυτό παρά μόνο αφού παρέλθουν σαράντα (40) λεπτά από την έναρξη της εξέτασης του μαθήματος."
    },
    {
      "provision_ref": "sec18",
      "section": "18",
      "title": "Άρθρο 18: Λειτουργοί που εμπλέκονται στη διαδικασία θεματοθέτησης",
      "content": "18. (α) Οι εντεταλμένοι από την Υπηρεσία Εξετάσεων λειτουργοί, που εμπλέκονται στη διαδικασία θεματοθέτησης, αποστολής των εξεταστικών δοκιμίων στα εξεταστικά κέντρα και βαθμολόγησης, υπογράφουν Υπεύθυνη Δήλωση, όπως αυτή καθορίζεται στο Παράρτημα ΙΙΙ.\n(β) Λειτουργοί που ανήκουν στο προσωπικό της Υπηρεσίας Εξετάσεων και έχουν συγγενή μέχρι και τον τέταρτο βαθμό συγγένειας, εξ αίματος ή εξ αγχιστείας, που είναι υποψήφιος στις Παγκύπριες Εξετάσεις Πρόσβασης, το δηλώνουν στην αρμόδια αρχή, η οποία και αποφασίζει το βαθμό συμμετοχής τους στη διαδικασία."
    },
    {
      "provision_ref": "sec19",
      "section": "19",
      "title": "Άρθρο 19: Κριτήρια επιλογής βαθμολογητών",
      "content": "19. Τα κριτήρια επιλογής των βαθμολογητών των Παγκύπριων Εξετάσεων Πρόσβασης είναι τα ακόλουθα:\n(α) Αναγνωρισμένη εκπαιδευτική υπηρεσία τουλάχιστον πέντε (5) ετών.\n(β) Διδασκαλία του υπό εξέταση μαθήματος στην Γ’ Λυκείου ή σε Τεχνικές Σχολές κατά το έτος που είναι βαθμολογητές ή τουλάχιστον κατά το προηγούμενο έτος.\n(γ) Διδασκαλία του υπό εξέταση μαθήματος για τουλάχιστον πέντε (5) χρόνια στη Γ’ Λυκείου ή σε Τεχνικές Σχολές.\n(δ) Η μη παράδοση φροντιστηριακών μαθημάτων και η μη διδασκαλία μαθημάτων των Παγκύπριων Εξετάσεων στα Κρατικά Ινστιτούτα Επιμόρφωσης (Κ.Ι.Ε.) ή στα βραδινά τμήματα των Τεχνικών Σχολών ή αλλού, να μην είναι ιδιοκτήτες Φροντιστηρίου ή να μην έχουν άμεση ή έμμεση σχέση με ιδιοκτήτη Φροντιστηρίου.\n(ε) Η μη ανάληψη καθηκόντων βαθμολόγησης, όπου είναι δυνατό, σε περισσότερα από δύο (2) μαθήματα.\n(στ) Η συμμετοχή σε υποχρεωτικά σεμινάρια επιμόρφωσης που οργανώνονται για το σκοπό αυτό από την Υπηρεσία Εξετάσεων του Υπουργείου Παιδείας και Πολιτισμού."
    },
    {
      "provision_ref": "sec20",
      "section": "20",
      "title": "Άρθρο 20: Επιλογή βαθμολογητών",
      "content": "20. Η επιλογή των βαθμολογητών γίνεται από τριμελή επιτροπή της οποίας προεδρεύει ο/η Προϊστάμενος/η της Υπηρεσίας Εξετάσεων και συμμετέχουν ως μέλη οι Διευθυντές Μέσης Γενικής και Μέσης Τεχνικής και Επαγγελματικής Εκπαίδευσης, ανάλογα με το μάθημα εξέτασης, και ένας Επιθεωρητής Μέσης Εκπαίδευσης της ειδικότητας ή συναφούς ειδικότητας με το εξεταζόμενο μάθημα."
    },
    {
      "provision_ref": "sec21",
      "section": "21",
      "title": "Άρθρο 21: Επιμόρφωση βαθμολογητών",
      "content": "21.-(1) Η Υπηρεσία Εξετάσεων, σε συνεργασία με τις Διευθύνσεις Μέσης Γενικής και Μέσης Τεχνικής και Επαγγελματικής Εκπαίδευσης και το Παιδαγωγικό Ινστιτούτο Κύπρου, καθορίζει τις διαδικασίες επιμόρφωσης των βαθμολογητών.\n(2) Η επιμόρφωση των βαθμολογητών είναι συστηματική, ξεκινά από το φθινόπωρο κάθε έτους και περιλαμβάνει επιμορφωτικά σεμινάρια, τα οποία έχουν βιωματική μορφή και περιλαμβάνουν δοκιμαστική βαθμολόγηση γραπτών.\n(3) Η επιμόρφωση καταλήγει στη δημιουργία στατιστικού προφίλ για κάθε βαθμολογητή ξεχωριστά.\n(4) Η πιστοποίηση της επάρκειας κάθε βαθμολογητή ανανεώνεται ετησίως και του παρέχει τη δυνατότητα να συνεχίζει να ανήκει στο μητρώο των βαθμολογητών που τηρεί η Υπηρεσία Εξετάσεων."
    },
    {
      "provision_ref": "sec22",
      "section": "22",
      "title": "Άρθρο 22: Υποχρεώσεις βαθμολογητών",
      "content": "22.-(1) Οι οριζόμενοι βαθμολογητές υπογράφουν Υπεύθυνη Δήλωση, όπως αυτή καθορίζεται στο Παράρτημα ΙΙΙ.\n(2)(α) Στον κάθε βαθμολογητή αναλογεί συγκεκριμένος αριθμός τετραδίων απαντήσεων των υποψηφίων, τα οποία οφείλει να βαθμολογήσει με εμπιστευτικότητα και να τα φυλάξει, σύμφωνα με τις οδηγίες που καθορίζει η Υπηρεσία Εξετάσεων, ασφαλισμένα εντός του βαθμολογικού κέντρου, ώστε να μην υπάρχει δυνατότητα πρόσβασης σ’ αυτά από μη εξουσιοδοτημένα πρόσωπα ή απώλειάς τους·\n(β) Ο βαθμολογητής-\n(i) Δίδει τη βαθμολογία κατά ερώτηση και το σύνολο της βαθμολογίας στην κατάλληλη θέση του τετραδίου.\n(ii) δεν σημειώνει οτιδήποτε στο γραπτό.\n(iii) αν διαπιστώσει στοιχεία που δημιουργούν υπόνοιες για δολίευση, επικοινωνεί με τον οριζόμενο από την Υπηρεσία Εξετάσεων υπεύθυνο του κέντρου βαθμολόγησης και αναφέρει τα σχετικά στοιχεία.\n(iv) δύναται να κληθεί από την Υπηρεσία Εξετάσεων για αποκατάσταση τυχόν αβλεψίας, λάθους ή παράλειψής του που παρατηρείται μετά την εκ μέρους του βαθμολόγηση του γραπτού τετραδίου και είναι υποχρεωμένος να μεταβεί στο κέντρο βαθμολόγησης για αποκατάσταση της αβλεψίας, του λάθους ή της παράλειψης που θα εντοπιστεί από την Υπηρεσία Εξετάσεων, σύμφωνα με του κανόνες καλής πρακτικής που εφαρμόζει η Υπηρεσία Εξετάσεων."
    },
    {
      "provision_ref": "sec23",
      "section": "23",
      "title": "Άρθρο 23: Δοκιμαστική βαθμολόγηση των μαθημάτων",
      "content": "23.-(1)(α) Πριν από τη βαθμολόγηση των εξεταστικών δοκιμίων των εξεταζόμενων μαθημάτων που περιλαμβάνονται στα πλαίσια πρόσβασης, γίνεται συντονισμός των βαθμολογητών από μέλη της Επιτροπής Θεματοθετών του κάθε μαθήματος και δίνεται γραπτώς ο λεπτομερής οδηγός διόρθωσης ως προς τον τρόπο βαθμολόγησης όλων των μερών του εξεταστικού δοκιμίου.\n(β) Ο οδηγός διόρθωσης συμπληρώνεται, διαφοροποιείται και ολοκληρώνεται μετά το συντονισμό των βαθμολογητών και αφού ληφθούν υπόψη όλες οι βάσιμες και τεκμηριωμένες εισηγήσεις που υποβάλλονται από όλους τους συμμετέχοντες στη διαδικασία.\n(γ) Η Υπηρεσία Εξετάσεων και η ομάδα που είναι υπεύθυνη για τη σύνταξη του τελικού οδηγού διόρθωσης αποφασίζουν για τη διαδικασία ποιοτικού ελέγχου της βαθμολόγησης των γραπτών τετραδίων και καθορίζουν τις ειδικές παραμέτρους κάθε εξεταζόμενου μαθήματος, όπως οι μέγιστες επιτρεπόμενες διαφορές μεταξύ των βαθμολογιών των βαθμολογητών ανά ερώτηση.\n(2) Πριν από την κανονική βαθμολόγηση των γραπτών τετραδίων γίνεται δοκιμαστική βαθμολόγηση, κατά την οποία-\n(α) Επιλέγεται τυχαία αριθμός γραπτών τετραδίων τα οποία φωτοτυπούνται σε τόσα αντίγραφα όσοι είναι και οι βαθμολογητές.\n(β) δίνονται τα ίδια αντίγραφα σε όλους τους βαθμολογητές, οι οποίοι τα βαθμολογούν σύμφωνα με τις οδηγίες της Επιτροπής Θεματοθετών.\n(γ) όταν τα μέλη της Επιτροπής Θεματοθετών βεβαιωθούν ότι γίνεται ομοιόμορφη βαθμολόγηση, τότε οι βαθμολογητές προχωρούν στην κανονική βαθμολόγηση των τετραδίων απαντήσεων των υποψηφίων.\n(δ) η Υπηρεσία Εξετάσεων επεξεργάζεται τις βαθμολογίες και δίνει στοιχεία στην Επιτροπή Θεματοθετών και στους βαθμολογητές ως προς τον τρόπο βαθμολόγησής τους.\n(ε) στην περίπτωση που διαπιστωθεί ότι κάποιος βαθμολογητής παρουσιάζει σοβαρή απόκλιση από τους υπόλοιπους κατά τη δοκιμαστική ή την κανονική βαθμολόγηση των τετραδίων απαντήσεων των υποψηφίων, η Υπηρεσία Εξετάσεων δύναται να τον αποκλείει από τη διαδικασία κανονικής βαθμολόγησης."
    },
    {
      "provision_ref": "sec24",
      "section": "24",
      "title": "Άρθρο 24: Βαθμολόγηση - Αναβαθμολόγηση των γραπτών δοκιμίων, των μαθημάτων που περιλαμβάνονται στα πλαίσια πρόσβασης",
      "content": "24.- (1) Κάθε γραπτό βαθμολογείται από δύο βαθμολογητές ως ακολούθως:\n(α) Ο πρώτος βαθμολογητής σημειώνει τους βαθμούς κατά ερώτηση και το σύνολο της βαθμολογίας του στον ειδικό χώρο του τετραδίου απαντήσεων και, αφού τους καλύψει αδιαφανώς, παραδίδει τα τετράδια απαντήσεων των υποψηφίων στον εντεταλμένο, από την Υπηρεσία Εξετάσεων, υπεύθυνο του βαθμολογικού κέντρου.\n(β) ο δεύτερος βαθμολογητής σημειώνει τους βαθμούς κατά ερώτηση και το σύνολο της βαθμολογίας του σε άλλο ειδικό χώρο του τετραδίου απαντήσεων των υποψηφίων και παραδίδει τα τετράδια απαντήσεων στον εντεταλμένο, από την Υπηρεσία Εξετάσεων, υπεύθυνο του βαθμολογικού κέντρου.\n(2) Μετά τη βαθμολόγηση του τετραδίου απαντήσεων των υποψηφίων και από το δεύτερο βαθμολογητή, αποκαλύπτεται με ευθύνη και επίβλεψη της Υπηρεσίας Εξετάσεων η πρώτη βαθμολογία και συγκρίνεται με τη δεύτερη και εφόσον αποκλειστεί κατά το μέγιστο δυνατό βαθμό η πιθανότητα λάθους ή αβλεψίας από τους βαθμολογητές κατά την καταχώρηση της βαθμολογίας τους με μια σειρά οπτικών και άλλων ελέγχων, η Υπηρεσία Εξετάσεων προβαίνει στην καταχώρηση του συνολικού βαθμού του τετραδίου απαντήσεων του υποψηφίου:\nΝοείται ότι, σε περίπτωση κατά την οποία, μεταξύ των δύο συνολικών βαθμολογιών δεν υπάρχει συνολική διαφορά μεγαλύτερη από το δέκα τοις εκατόν (10%) της μέγιστης δυνατής βαθμολογίας του μαθήματος, τότε το άθροισμα των δύο βαθμολογιών αποτελεί το βαθμό στο μάθημα.\n(3) Σε περίπτωση κατά την οποία μεταξύ των δυο συνολικών βαθμολογιών υπάρχει διαφορά μεγαλύτερη από το δέκα τοις εκατόν (10%) της μέγιστης δυνατής βαθμολογίας του μαθήματος, τότε το τετράδιο απαντήσεων αναβαθμολογείται με την ακόλουθη διαδικασία:\n(α) Καλύπτονται οι βαθμολογίες των δύο βαθμολογητών και ο αναβαθμολογητής βαθμολογεί το τετράδιο απαντήσεων χωρίς να τις γνωρίζει.\n(β) Ο τελικός βαθμός του τετραδίου απαντήσεων των υποψηφίων είναι το διπλάσιο του μέσου όρου των τριών βαθμολογιών των δύο βαθμολογητών και του αναβαθμολογητή και δεν επιδέχεται αναθεώρησης.\n(4) Επανεξέταση των τετραδίων απαντήσεων των υποψηφίων ή άλλη αναβαθμολόγηση δεν επιτρέπεται.\n(5) Ο τελικός βαθμός του τετραδίου απαντήσεων του υποψηφίου κάθε μαθήματος δυνατό να υπόκειται σε στατιστική επεξεργασία από την Υπηρεσία Εξετάσεων, σύμφωνα με οδηγίες της αρμόδιας αρχής, οι οποίες δημοσιεύονται στον Οδηγό Παγκύπριων Εξετάσεων Πρόσβασης πριν από τη διενέργεια των εξετάσεων.\n(6) Σε περίπτωση που βαθμολογητής αποκλειστεί από τη διαδικασία βαθμολόγησης, σύμφωνα με τις διατάξεις της παραγράφου (ε) του εδαφίου (2) του άρθρου 23, η βαθμολόγηση όλων των τετραδίων απαντήσεων που έχει στο μεταξύ βαθμολογήσει ακυρώνεται και αυτά τα τετράδια απαντήσεων κατανέμονται στους υπόλοιπους βαθμολογητές για επαναβαθμολόγηση."
    },
    {
      "provision_ref": "sec25",
      "section": "25",
      "title": "Άρθρο 25: Εξεταστικά κέντρα",
      "content": "25.-(1) Τα εξεταστικά κέντρα καθορίζονται από τις Διευθύνσεις Μέσης Εκπαίδευσης και ανακοινώνονται κάθε χρόνο από την Υπηρεσία Εξετάσεων, το αργότερο μέχρι την εικοστή ημέρα του μηνός Απριλίου κάθε έτους, με σχετική δημοσίευση στην επίσημη ιστοσελίδα της Υπηρεσίας Εξετάσεων ή/και σε ημερήσιες, παγκύπριας κυκλοφορίας, εφημερίδες ή/και με εγκύκλιο που αποστέλλεται στα σχολεία Μέσης Εκπαίδευσης που καθορίζονται στην υποπαράγραφο (i) της παραγράφου (α) του άρθρου 6. Η Ειδική Επιτροπή Παροχής Διευκολύνσεων καθορίζει το χώρο εξέτασης των υποψηφίων με ειδικές ανάγκες.\n(2) Οι υποψήφιοι ενημερώνονται ατομικά ή/και συλλογικά, ηλεκτρονικά μέσω της επίσημης ιστοσελίδας της Υπηρεσίας Εξετάσεων ή μέσω έντυπης επιστολής τουλάχιστο δύο (2) εβδομάδες πριν από την εξέταση, για το συγκεκριμένο εξεταστικό κέντρο στο οποίο θα λάβουν μέρος για κάθε μάθημα πρόσβασης που έχουν δηλώσει."
    },
    {
      "provision_ref": "sec26",
      "section": "26",
      "title": "Άρθρο 26: Στελέχωση και αρμοδιότητες Επιτροπής Εξεταστικού Κέντρου",
      "content": "26.-(1) Σε κάθε εξεταστικό κέντρο, με απόφαση της Διεύθυνσης του Σχολείου Μέσης Εκπαίδευσης που ορίζεται ως εξεταστικό κέντρο, συγκροτείται Επιτροπή Εξεταστικού Κέντρου που γνωστοποιείται εγγράφως στα μέλη της, έναν τουλάχιστο μήνα πριν την έναρξη των Παγκύπριων Εξετάσεων Πρόσβασης.\n(2) Η Επιτροπή Εξεταστικού Κέντρου αποτελείται από-\n(α) Τον πρόεδρο, ο οποίος δύναται να είναι ο Διευθυντής του σχολείου που λειτουργεί ως εξεταστικό κέντρο ή ένα Βοηθό Διευθυντή, που υποδεικνύεται από αυτόν ως εκπρόσωπός του,\n(β) ένα Βοηθό Διευθυντή, που ορίζεται από τον Διευθυντή του σχολείου, και\n(γ) πέντε (5) μέχρι εννέα (9) μέλη του διδακτικού προσωπικού, ανάλογα με το μέγεθος του εξεταστικού κέντρου, που ορίζονται από τον Διευθυντή του σχολείου.\n(3) Η Επιτροπή Εξεταστικού Κέντρου-\n(α) Οργανώνει το εξεταστικό κέντρο,\n(β) εποπτεύει την ομαλή και αδιάβλητη διεξαγωγή των Παγκύπριων Εξετάσεων Πρόσβασης,\n(γ) κατανέμει τους επιτηρητές στις αίθουσες εξέτασης,\n(δ) καθορίζει τους αναπληρωτές επιτηρητές και τους τομείς ευθύνης τους,\n(ε) συγκεντρώνει και αποστέλλει τα τετράδια απαντήσεων των υποψηφίων στο καθορισμένο από την Υπηρεσία Εξετάσεων βαθμολογικό κέντρο,\n(στ) παρέχει διευκολύνσεις σε υποψηφίους με ειδικές ανάγκες, σύμφωνα με οδηγίες της Υπηρεσίας Εξετάσεων,\n(ζ) έχει την ευθύνη για την παραλαβή και τη διεκπεραίωση όλων των απαιτούμενων εργασιών που απορρέουν από τη διαδικασία αποστολής των εξεταστικών δοκιμίων στα εξεταστικά κέντρα, όπως καθορίζεται από την αρμόδια αρχή και\n(η) λαμβάνει κάθε μέτρο που απαιτείται για την απρόσκοπτη διεξαγωγή των Παγκύπριων Εξετάσεων Πρόσβασης.\n(4) Τόσο η διαδικασία αποστολής όσο και τα καθήκοντα των Επιτροπών Εξεταστικών Κέντρων αναγράφονται αναλυτικά στον Οδηγό Παγκύπριων Εξετάσεων Πρόσβασης.\n(5) Για τη διευκόλυνση του έργου της Επιτροπής Εξεταστικού Κέντρου, τα μέλη της απαλλάσσονται από τις μη διδακτικές εργασίες του σχολείου κατά την περίοδο των Παγκύπριων Εξετάσεων Πρόσβασης, όχι όμως και από τη βαθμολόγηση γραπτών και την έκδοση αποτελεσμάτων των μαθητών τους."
    },
    {
      "provision_ref": "sec27",
      "section": "27",
      "title": "Άρθρο 27: Καθορισμός και υποχρεώσεις επιτηρητών και αναπληρωτών επιτηρητών",
      "content": "27.-(1) Οι επιτηρητές και οι αναπληρωτές επιτηρητές είναι καθηγητές ή εκπαιδευτές δημόσιου σχολείου Μέσης Εκπαίδευσης και ο αριθμός τους ανά σχολείο ορίζεται από τις Διευθύνσεις Μέσης Εκπαίδευσης, σύμφωνα με τις ανάγκες σε αίθουσες στο συγκεκριμένο εξεταστικό κέντρο, όπως καθορίζονται από την Υπηρεσία Εξετάσεων.\n(2) Σε κάθε αίθουσα εξέτασης ορίζονται τουλάχιστο δύο επιτηρητές, μεταξύ των οποίων κατανέμεται η εργασία και λειτουργούν συνυπεύθυνα.\n(3) Οι επιτηρητές-\n(α) Απαγορεύεται να δίνουν διευκρινίσεις αναφορικά με το εξεταστικό δοκίμιο, είναι δυνατό όμως να βοηθήσουν τους υποψηφίους να συμπληρώσουν σωστά τα στοιχεία τους και τον κωδικό του μαθήματος στο τετράδιο απαντήσεων.\n(β) υποχρεούνται να λαμβάνουν όλα τα αναγκαία μέτρα, ώστε η εξέταση να διεξάγεται ομαλά και να αποφεύγεται η δολίευση.\n(γ) προσέρχονται στο εξεταστικό κέντρο τουλάχιστον τριάντα λεπτά πριν και στην αίθουσα εξέτασης τουλάχιστον είκοσι λεπτά πριν από την καθορισμένη ώρα έναρξης της εξέτασης.\n(δ) παραλαμβάνουν τα εξεταστικά δοκίμια και τα τετράδια απαντήσεων των υποψηφίων από την Επιτροπή Εξεταστικού Κέντρου, ανοίγουν το φάκελο στην παρουσία των υποψηφίων και τους διανέμουν τα δοκίμια στον καθορισμένο χρόνο.\n(ε) ελέγχουν ότι οι υποψήφιοι δεν έχουν μαζί τους οτιδήποτε απαγορεύεται να φέρουν, σύμφωνα με την παράγραφο (α) του εδαφίου (7) του άρθρου 31 ή οποιοδήποτε αντικείμενο που είναι δυνατό να χρησιμοποιηθεί στις Παγκύπριες Εξετάσεις Πρόσβασης με σκοπό τη δολίευση.\n(στ) επιτρέπουν τη χρήση εγκεκριμένης μη προγραμματιζόμενης υπολογιστικής μηχανής μόνο στην εξέταση στα καθορισμένα στον Οδηγό Παγκύπριων Εξετάσεων Πρόσβασης μαθήματα.\n(ζ) απαγορεύουν τη χρήση υπολογιστικής μηχανής, η οποία δεν έχει ελεγχθεί και σφραγιστεί από την Επιτροπή Εξεταστικού Κέντρου, σε χρόνο και με τρόπο που καθορίζει και ανακοινώνει δημόσια η αρμόδια αρχή και η οποία οπωσδήποτε δεν πρέπει να επιδέχεται προγραμματισμό:\nΝοείται ότι η χρήση μη εγκεκριμένης υπολογιστικής μηχανής θεωρείται ως απόπειρα δολίευσης.\n(η) γράφουν στον πίνακα της αίθουσας εξέτασης το χρόνο έναρξης και λήξης της εξέτασης.\n(θ) πριν από την έναρξη της εξέτασης δίνουν οδηγίες στους υποψηφίους να γράψουν τα ατομικά τους στοιχεία στο ειδικό πλαίσιο του εξώφυλλου του τετραδίου απαντήσεων και κατά τη διάρκεια της εξέτασης ελέγχουν την ταυτότητα ή το διαβατήριο και το δελτίο υποψηφίου και τα συγκρίνουν με τα ατομικά στοιχεία που ο υποψήφιος έγραψε στο τετράδιο απαντήσεων.\n(ι) δύναται να επιτρέψουν, κατ΄ εξαίρεση, την είσοδο, ύστερα από απόφαση του προέδρου της Επιτροπής Εξεταστικού Κέντρου ή εκπροσώπου του, σε υποψήφιο που καθυστέρησε να προσέλθει στην αίθουσα εξέτασης, όχι όμως μετά από την παρέλευση σαράντα (40) λεπτών από τη διανομή των εξεταστικών δοκιμίων στους υποψηφίους:\nΝοείται ότι, στους υποψηφίους που καθυστέρησαν να προσέλθουν στην εξέταση, δεν παραχωρείται πρόσθετος από τον προκαθορισμένο χρόνος για ολοκλήρωση της εξέτασης αυτής, όπως αυτός καθορίζεται στο Πρόγραμμα των Παγκύπριων Εξετάσεων.\n(ια) κατά την παράδοση των γραπτών, καλύπτουν με το αδιαφανές κάλυμμα το ειδικό πλαίσιο τoυ εξωφύλλου των τετραδίων απαντήσεων στα οποία είναι γραμμένα τα ατομικά στοιχεία των υποψηφίων, αφού προηγουμένως διεξάγουν το σχετικό έλεγχο των ονομαστικών στοιχείων, συγκρίνοντάς τα με τα στοιχεία του δελτίου υποψηφίου και τα στοιχεία της ταυτότητας ή του διαβατηρίου του και ελέγχουν με ιδιαίτερη προσοχή αν υπάρχει σημείωση ονομαστικών ή άλλων διακριτικών στοιχείων, τα οποία είναι δυνατό να αποκαλύψουν την ταυτότητα του υποψηφίου.\n(ιβ) μονογράφουν στο τέλος των απαντήσεων του υποψηφίου στο τετράδιο απαντήσεων και ακυρώνουν με διαγώνια ευθεία τους κενούς χώρους.\n(ιγ) σημειώνουν τον αριθμό της αίθουσας εξέτασης και τους παρόντες στον κατάλογο υποψηφίων, γράφοντας ανάλογα τη λέξη παρών/απών στον κατάλληλο χώρο και καταγράφοντας το συνολικό αριθμό των παρόντων.\n(ιδ) συμπληρώνουν τα δικά τους στοιχεία και υπογράφουν στον κατάλογο υποψηφίων.\n(ιε) σε περίπτωση υπόνοιας για δολίευση ή για απόπειρα δολίευσης, παραλαμβάνουν τα σχετικά τεκμήρια, καλούν επί τόπου τον πρόεδρο της Επιτροπής Εξεταστικού Κέντρου ή εκπρόσωπό του και ακούουν την άποψη του υποψηφίου η οποία καταγράφεται˙\n(ιστ) εφόσον διαπιστωθεί και από τον πρόεδρο της Επιτροπής Εξεταστικού Κέντρου δολίευση ή απόπειρα δολίευσης, οι επιτηρητές παίρνουν το γραπτό του υποψηφίου που δολιεύθηκε ή αποπειράθηκε να δολιευτεί και τον αποπέμπουν από την αίθουσα.\n(ιζ) καταγράφουν συνοδευτική παρατήρηση πάνω στο γραπτό του υποψήφιου που δολιεύθηκε ή αποπειράθηκε να δολιευτεί και το παραδίδουν στον πρόεδρο της Επιτροπής Εξεταστικού Κέντρου:\nΝοείται ότι ο υποψήφιος, εάν το επιθυμεί, δύναται να παραδώσει στον επιτηρητή ή στον Πρόεδρο της Επιτροπής Εξεταστικού Κέντρου το δικό του γραπτό σημείωμα με την άποψή του για τα γεγονότα, το οποίο θα πρέπει απαραίτητα να επισυναφθεί μαζί με τις άλλες εκθέσεις που αφορούν το περιστατικό. και\n(ιη) παραδίδουν τα τετράδια απαντήσεων με τον κατάλογο των παρόντων υποψηφίων στον πρόεδρο της Επιτροπής Εξεταστικού Κέντρου.\n(4) Οι αναπληρωτές επιτηρητές-\n(α) Βρίσκονται καθ’ όλη τη διάρκεια της εξέτασης στον τομέα ευθύνης τους, έχοντας οπτική επαφή με όλες τις αίθουσες στις οποίες γίνεται εξέταση.\n(β) αναλαμβάνουν καθήκοντα επιτηρητή, όταν καλούνται από κάποιον επιτηρητή, αφού ενημερώσουν σχετικά τον πρόεδρο της Επιτροπής Εξεταστικού Κέντρου. και\n(γ) αναλαμβάνουν οποιαδήποτε άλλα καθήκοντα τους αναθέσει ο πρόεδρος της Επιτροπής Εξεταστικού Κέντρου για την ομαλή διεξαγωγή των Παγκύπριων Εξετάσεων Πρόσβασης.\n(5) Παράταση χρόνου ή και άλλες δυνατές διευκολύνσεις παρέχονται μόνο σε υποψηφίους με ειδικές ανάγκες, οι οποίοι, μετά από αίτησή τους, έχουν λάβει σχετική απόφαση από την Ειδική Επιτροπή Παροχής Διευκολύνσεων για τις Παγκύπριες Εξετάσεις Πρόσβασης, η οποία προσκομίζεται στα υπεύθυνα για το θέμα μέλη των επιτροπών των εξεταστικών κέντρων:\nΝοείται ότι ο χρόνος εξέτασης οποιουδήποτε υποψηφίου δεν παρατείνεται σε καμιά άλλη περίπτωση:\nΝοείται περαιτέρω ότι οι διευκολύνσεις αυτές εγκρίνονται από την Ειδική Επιτροπή, η οποία ορίζεται και έχει αρμοδιότητα σύμφωνα με τις διατάξεις του άρθρου 11 του παρόντος Νόμου.\n(6)(α) Σε περίπτωση κατά την οποία κατά τη διάρκεια της εξέτασης υπάρξει υπόνοια πλαστοπροσωπίας, οι επιτηρητές ή οι αναπληρωτές επιτηρητές ενημερώνουν αμέσως τον πρόεδρο της Επιτροπής Εξεταστικού Κέντρου, ο οποίος λαμβάνει αμέσως μέτρα για αναγνώριση της ταυτότητας του υποψηφίου. για τους σκοπούς της παρούσας παραγράφου, οι επιτηρητές ή οι αναπληρωτές επιτηρητές επιτρέπουν στον υποψήφιο να λάβει μέρος στην εξέταση κανονικά, αλλά δεν επιτρέπουν την αναχώρησή του από την αίθουσα εξέτασης, προτού αναγνωριστεί η ταυτότητά του.\n(β) Ο πρόεδρος της Επιτροπής Εξεταστικού Κέντρου δίνει γραπτώς πλήρη περιγραφή των γεγονότων και αποστέλλει στην Υπηρεσία Εξετάσεων-\n(i) Υπογραμμένη αναφορά από τους επιτηρητές,\n(ii) υπογραμμένη δήλωση του υποψηφίου, αν έχει υποβληθεί,\n(iii) οποιοδήποτε τεκμήριο υπάρχει."
    },
    {
      "provision_ref": "sec28",
      "section": "28",
      "title": "Άρθρο 28: Δικαίωμα διεκδίκησης θέσης στα Δημόσια ΑΑΕΙ",
      "content": "28. Δικαίωμα διεκδίκησης θέσης έχουν όσοι από τους υποψηφίους κατά την ημερομηνία της κατανομής των θέσεων-\n(α) Έχουν υποβάλει στην Υπηρεσία Εξετάσεων απολυτήριο ή βεβαίωση απόλυσης που εκδίδει το σχολείο τους, το οποίο πρέπει να πληρεί τις προϋποθέσεις του άρθρου 6 του παρόντος Νόμου,\n(β) πληρούν τις προϋποθέσεις πρόσβασης που καθορίζει η αρμόδια αρχή, και\n(γ) έχουν εξασφαλίσει βαθμό κατάταξης."
    },
    {
      "provision_ref": "sec29",
      "section": "29",
      "title": "Άρθρο 29: Κατανομή και προσφορά θέσεων στα Δημόσια ΑΑΕΙ προς τους υποψηφίους",
      "content": "29.-(1)(α) Υποψήφιοι που έχουν εξασφαλίσει δικαίωμα διεκδίκησης θέσης τοποθετούνται στη σειρά με κριτήριο το βαθμό κατάταξης που συγκέντρωσε ο καθένας ανά πλαίσιο πρόσβασης.\n(β) Ακολουθεί η πρώτη κατανομή και η προσφορά των θέσεων, αρχίζοντας από τον πρώτο στη σειρά επιτυχίας και με βάση τη δήλωση προτίμησης ικανοποιείται η καλύτερη, στη σειρά προτίμηση των υποψηφίων όπως τους επιτρέπει η σειρά επιτυχίας τους.\n(γ) Τηρουμένων των διατάξεων των υποπαραγράφων (α) και (β), ολοκληρώνεται η πρώτη κατανομή των υποψηφίων στις διαθέσιμες θέσεις των Δημόσιων ΑΑΕΙ της Κύπρου.\n(2)(α) Η Υπηρεσία Εξετάσεων ενημερώνει είτε ηλεκτρονικώς είτε με άλλο τρόπο κάθε υποψήφιο για τις αρχικές βαθμολογίες, τις βαθμολογίες ανά πλαίσιο πρόσβασης και για τη θέση που εξασφάλισε.\n(β) Η πρώτη κατανομή δημοσιεύεται στην επίσημη ιστοσελίδα του Υπουργείου Παιδείας και Πολιτισμού.\n(γ) Τεκμαίρεται ότι, υποψήφιος αποδέχεται τη θέση, εκτός εάν δηλώσει προς τα Δημόσια ΑΑΕΙ της Κύπρου, εντός της καθορισμένης προθεσμίας, ότι δεν ενδιαφέρεται για τη θέση ή ότι ενδιαφέρεται να συμμετάσχει σε ενδεχόμενη δεύτερη κατανομή.\n(3)(α) Μετά την υποβολή των δηλώσεων εκ μέρους των υποψηφίων και την πληροφόρηση από τα Δημόσια ΑΑΕΙ της Κύπρου για τυχόν ύπαρξη κενών θέσεων, η αρμόδια αρχή αποφασίζει αν θα γίνει δεύτερη ή και τρίτη κατανομή των θέσεων.\n(β) Σε περίπτωση που αποφασιστεί να γίνει δεύτερη ή/και τρίτη κατανομή των θέσεων, η Υπηρεσία Εξετάσεων, η οποία διενεργεί τη δεύτερη ή/και την τρίτη κατανομή, ανακοινώνει τις διαδικασίες που ακολουθούνται για τη δεύτερη ή/και τρίτη κατανομή.\n(4) Αν διαπιστωθεί λάθος στην προσφορά θέσης σε οποιοδήποτε στάδιο της διαδικασίας βαθμολογίας των τετραδίων απαντήσεων των υποψηφίων και της κατανομής των θέσεων, η Υπηρεσία Εξετάσεων έχει το δικαίωμα να αφαιρέσει ή και να τροποποιήσει την προσφορά θέσης, ούτως ώστε η τελική κατανομή να γίνεται αυστηρά με βάση τη σειρά επιτυχίας και τις προτιμήσεις κάθε υποψηφίου, όπως αυτές δηλώνονται στην αίτηση που υποβάλλεται για συμμετοχή στις Παγκύπριες Εξετάσεις Πρόσβασης.\n(5) Με απόφαση της αρμόδιας αρχής κατανέμονται κατ’ έτος ως υπεράριθμες θέσεις σε συγκεκριμένες Σχολές/Τμήματα, σε ποσοστό ίσο με το δέκα τοις εκατόν (10%) του συνολικού αριθμού θέσεων στις συγκεκριμένες Σχολές/Τμήματα, με δικαιούχους τους μαθητές της τελευταίας τάξης και τους απόφοιτους των δημόσιων Τεχνικών Σχολών και του Eξατάξιου Γυμνασίου Κάτω Πύργου, που λειτουργούν σύμφωνα με τους περί Λειτουργίας των Δημόσιων Σχολείων Μέσης Εκπαίδευσης Κανονισμούς, και σε ποσοστό ίσο με το τρία τοις εκατόν (3%) με δικαιούχους τους μαθητές της τελευταίας τάξης και τους αποφοίτους των δημόσιων Εσπερινών Γυμνασίων και Εσπερινών Τεχνικών Σχολών:\nΝοείται ότι οι πιο πάνω δικαιούχοι έχουν εξασφαλίσει βαθμό κατάταξης τουλάχιστον εβδομήντα τοις εκατόν (70%) του βαθμού κατάταξης του τελευταίου υποψηφίου που εισήχθη στο Τμήμα/Σχολή της προτίμησης των εν λόγω δικαιούχων και πληρούν τις προϋποθέσεις πρόσβασης για το Τμήμα/Σχολή αυτό/ή:\nΝοείται περαιτέρω ότι θέσεις που δεν περιλαμβάνονται στις υπεράριθμες και καταλαμβάνονται από τελειοφοίτους και αποφοίτους Εξατάξιου Γυμνασίου Κάτω Πύργου, δημόσιων Τεχνικών Σχολών, δημόσιων Εσπερινών Γυμνασίων και δημόσιων Εσπερινών Τεχνικών Σχολών δεν υπολογίζονται στις υπεράριθμες θέσεις που αναφέρονται πιο πάνω και οι διαθέσιμες υπεράριθμες θέσεις δεν μειώνονται από τυχόν εξασφάλιση εκ μέρους των πιο πάνω υποψηφίων άλλης θέσης στα πλαίσια των Παγκύπριων Εξετάσεων Πρόσβασης:\nΝοείται έτι περαιτέρω ότι, μαθητές της τελευταίας τάξης και απόφοιτοι του Εξατάξιου Γυμνασίου Κάτω Πύργου καθίστανται δικαιούχοι, νοουμένου ότι φοιτούν στο εν λόγω σχολείο τουλάχιστον κατά το τελευταίο έτος της φοίτησής τους στον λυκειακό κύκλο.\n(6) Υποψήφιος, ο οποίος κατά τον ουσιώδη χρόνο που εξασφαλίζει θέση σε Δημόσια ΑΑΕΙ της Κύπρου, εκτελεί κανονική ή εναλλακτική στρατιωτική θητεία, κατοχυρώνει τη θέση αυτή μέχρι την ολοκλήρωση της θητείας αυτής.\n(7) Ανεξάρτητα από τις διατάξεις του παρόντος άρθρου, άτομα που εντάσσονται σε ειδικές κατηγορίες μπορούν να διεκδικήσουν αριθμό θέσεων ως υπεράριθμες, σε ποσοστό, με κριτήρια και με διαδικασίες που καθορίζονται με κανονισμούς:\nΝοείται ότι μέχρι την έκδοση κανονισμών, το ποσοστό, τα κριτήρια και οι διαδικασίες καθορίζονται με κανόνες των Δημόσιων ΑΑΕΙ."
    },
    {
      "provision_ref": "sec30",
      "section": "30",
      "title": "Άρθρο 30: Οδηγός Παγκύπριων Εξετάσεων Πρόσβασης",
      "content": "30. Με σκοπό τη λεπτομερή ενημέρωση των υποψηφίων, η αρμόδια αρχή εκδίδει κάθε χρόνο σύμφωνα με το άρθρο 38 του παρόντος Νόμου, το αργότερο μέχρι την 31η Ιανουαρίου, Οδηγό Παγκύπριων Εξετάσεων Πρόσβασης που περιέχει-\n(α) Τις γενικές οδηγίες για τους υποψηφίους,\n(β) τα Τμήματα των Δημόσιων ΑΑΕΙ της Κύπρου,\n(γ) τα εξεταζόμενα μαθήματα ανά πλαίσιο πρόσβασης,\n(δ) την εξεταστέα ύλη για κάθε μάθημα,\n(ε) τη διαδικασία αποστολής των εξεταστικών δοκιμίων στα εξεταστικά κέντρα, η οποία καθορίζεται από την αρμόδια αρχή,\n(στ) δειγματικά εξεταστικά δοκίμια ή/και εξεταστικά δοκίμια από προηγούμενες εξετάσεις,\n(ζ) το πρόγραμμα και τις ημερομηνίες εξετάσεων για κάθε μάθημα,\n(η) τα τέλη για κάθε εξεταζόμενο μάθημα στις Παγκύπριες Εξετάσεις Πρόσβασης και\n(θ) οποιεσδήποτε άλλες διαδικασίες, προθεσμίες και πληροφορίες κρίνονται αναγκαίες από την αρμόδια αρχή για την καλύτερη εφαρμογή των διατάξεων του παρόντος Νόμου."
    },
    {
      "provision_ref": "sec31",
      "section": "31",
      "title": "Άρθρο 31: Υποχρεώσεις υποψηφίων",
      "content": "31.-(1) Οι υποψήφιοι προσέρχονται στην αίθουσα του εξεταστικού κέντρου τουλάχιστο δεκαπέντε (15) λεπτά πριν από την ώρα έναρξης της εξέτασης.\n(2) Τα ατομικά στοιχεία των υποψηφίων συμπληρώνονται από τους ιδίους κατά τη διάρκεια της εξέτασης στον ειδικό χώρο που υπάρχει στο εξώφυλλο του τετραδίου απαντήσεων και καλύπτονται αδιαφανώς από τον επιτηρητή κατά την παράδοση του τετραδίου από τους υποψηφίους.\n(3) (α) Η παράδοση του τετραδίου απαντήσεων από τους υποψηφίους που αποχωρούν από την αίθουσα εξέτασης είναι υποχρεωτική:\nΝοείται ότι η μη παράδοση του γραπτού από τον υποψήφιο συνεπάγεται το μηδενισμό του στη συγκεκριμένη εξέταση.\n(β) Η αποχώρηση υποψηφίου από την αίθουσα εξέτασης πριν περάσουν σαράντα (40) λεπτά από την ώρα έναρξης της εξέτασης απαγορεύεται.\n(4) Οι υποψήφιοι οφείλουν να γράφουν τις απαντήσεις, σε όσα μαθήματα υπάρχουν ερωτήσεις πολλαπλής επιλογής, στο φύλλο απαντήσεων που υπάρχει στο τετράδιο απαντήσεων και σε αντίθετη περίπτωση οι απαντήσεις δεν μπορούν να ληφθούν υπόψη. οι απαντήσεις πρέπει να είναι γραμμένες με πένα χρώματος μπλε, τα σχήματα μπορούν να γίνονται με μολύβι και δεν επιτρέπεται η χρησιμοποίηση διορθωτικού υγρού.\n(5) Η δολίευση ή η απόπειρα για δολίευση ή η άρνηση συμμόρφωσης προς τις υποδείξεις και συστάσεις των επιτηρητών συνεπάγεται την αποπομπή του εξεταζόμενου υποψηφίου από την αίθουσα και το μηδενισμό του γραπτού του στο συγκεκριμένο μάθημα.\n(6) Απαγορεύεται το κάπνισμα κατά τη διάρκεια της εξέτασης.\n(7)(α) Οι υποψήφιοι δεν επιτρέπεται να φέρουν στην αίθουσα εξέτασης-\n(i) Κινητό τηλέφωνο ή άλλη συσκευή στην οποία αποθηκεύονται πληροφορίες, όπως ηλεκτρονικό ρολόι χειρός,\n(ii) βιβλία, τετράδια, σημειώσεις, λογαριθμικούς ή άλλους πίνακες, προγραμματιζόμενες ηλεκτρονικές μηχανές ή οτιδήποτε άλλο σχετικό με το εξεταζόμενο μάθημα.\n(β) Η κατοχή των αναφερόμενων στις υποπαραγράφους (i) και (ii) κατά την ώρα της εξέτασης θεωρείται απόπειρα δολίευσης και τυγχάνουν εφαρμογής οι διαδικασίες περί δολίευσης.\n(8) Η μεταφορά κινητού τηλεφώνου ή άλλης ηλεκτρονικής συσκευής πληροφοριών στο χώρο του σχολείου κατά τις μέρες διεξαγωγής των εξετάσεων αποτελεί αποκλειστική ευθύνη των υποψηφίων.\n(9) Οι υποψήφιοι με ειδικές ανάγκες επιτρέπεται να φέρουν στην αίθουσα εξέτασης τον εξοπλισμό που καθορίζεται με απόφαση της Ειδικής Επιτροπής για Παροχή Διευκολύνσεων.\n(10) Η αρμόδια αρχή διατηρεί το δικαίωμα αφαίρεσης θέσης που προσφέρθηκε σε υποψήφιο, αν μετά από σχετική έρευνα αποδειχθεί ότι ο υποψήφιος είναι ένοχος δολίευσης ή πλαστοπροσωπίας."
    },
    {
      "provision_ref": "sec32",
      "section": "32",
      "title": "Άρθρο 32: Διαδικασία αναπαραγωγής, αποστολής και διανομής των εξεταστικών δοκιμίων των Παγκύπριων Εξετάσεων Πρόσβασης",
      "content": "32.-(1)(α) Η αρμόδια αρχή αποφασίζει τον τρόπο με τον οποίο αποστέλλονται κάθε χρόνο τα θέματα των Παγκύπριων Εξετάσεων Πρόσβασης στα εξεταστικά κέντρα, με γνώμονα τη διασφάλιση του απορρήτου και του αδιάβλητου των εξετάσεων.\n(β) Η ακριβής διαδικασία αποστολής των εξεταστικών δοκιμίων στα εξεταστικά κέντρα και η κατανομή αρμοδιοτήτων και ευθυνών αποφασίζεται από την αρμόδια αρχή, κοινοποιείται εγκαίρως και λεπτομερώς με εγκύκλιο του Υπουργείου Παιδείας και Πολιτισμού σε όλα τα εξεταστικά κέντρα και δημοσιεύεται στον Οδηγό Παγκύπριων Εξετάσεων Πρόσβασης.\n(2) Οι θεματοθέτες, ο/η δακτυλογράφος και όλοι οι εμπλεκόμενοι στη διαδικασία θεματοθέτησης και αποστολής των εξεταστικών δοκιμίων στα εξεταστικά κέντρα, δεν αποχωρούν από το κέντρο θεματοθέτησης προτού παρέλθουν σαράντα (40) λεπτά από την ώρα έναρξης της εξέτασης.\n(3) Τα εξεταστικά δοκίμια ανοίγονται και διανέμονται από τους επιτηρητές κάθε αίθουσας εξέτασης, στον καθορισμένο χρόνο και στην παρουσία των υποψηφίων.\n(4) Με εξαίρεση τους επιτηρητές και τα μέλη της Επιτροπής Εξεταστικού Κέντρου, δεν επιτρέπεται η είσοδος στις αίθουσες εξέτασης άλλου προσώπου, συμπεριλαμβανομένων και των εκπαιδευτικών που υπηρετούν στα εξεταστικά κέντρα, παρά μόνο σε έκτακτες περιπτώσεις και με τη σύμφωνη γνώμη του προέδρου του εξεταστικού κέντρου, επιτρέπεται η είσοδος σε προσωπικό για παροχή έκτακτης βοήθειας σε υποψηφίους.\n(5) Ο πρόεδρος της Επιτροπής Εξεταστικού Κέντρου, μετά το πέρας της εξέτασης και αφού συμπληρώσει το σχετικό έντυπο της Υπηρεσίας Εξετάσεων, παραδίδει τα γραπτά στο εντεταλμένο από την αρμόδια αρχή πρόσωπο, το οποίο τα μεταφέρει κατευθείαν στο συντονιστικό βαθμολογικό κέντρο.\n(6)(α) Η αρμόδια αρχή αποφασίζει τον τρόπο διεξαγωγής της εξέτασης των ειδικών μαθημάτων-\n(i) Της πρακτικής Δοκιμασίας και\n(ii) των Καλών Τεχνών.\n(β) Η διεξαγωγή των πιο πάνω εξετάσεων γίνεται σύμφωνα με τα όσα καθορίζονται στα Παραρτήματα Ι και ΙΙ.\n(γ) Η αρμόδια αρχή αποφασίζει τον τρόπο διεξαγωγής της εξέτασης οποιουδήποτε άλλου μαθήματος καθοριστεί από αυτή."
    },
    {
      "provision_ref": "sec33",
      "section": "33",
      "title": "Άρθρο 33: Λάθη στα εξεταστικά δοκίμια",
      "content": "33. Σε περίπτωση λάθους στα εξεταστικά δοκίμια δεν γίνεται καμιά διευκρίνιση ή διόρθωση κατά τη διάρκεια της εξέτασης, εκτός εάν δοθούν διαφορετικές οδηγίες από την αρμόδια αρχή:\nΝοείται ότι η αρμόδια αρχή αποφασίζει σε μεταγενέστερο στάδιο για τη σοβαρότητα του λάθους και καθορίζει με οδηγίες προς τους βαθμολογητές τον τρόπο με τον οποίο βαθμολογείται η ερώτηση."
    },
    {
      "provision_ref": "sec34",
      "section": "34",
      "title": "Άρθρο 34: Περίπτωση απώλειας γραπτού",
      "content": "34. Σε περίπτωση απώλειας τετραδίου απαντήσεων υποψηφίου, το οποίο απωλέσθηκε μετά την παράδοσή του από τον υποψήφιο στον επιτηρητή και μέχρι την έκδοση των αποτελεσμάτων, ο βαθμός του υποψηφίου-\n(α) Για εξεταζόμενο μάθημα στο οποίο ο υποψήφιος εξετάστηκε προηγουμένως κατά τις Παγκύπριες Εξετάσεις Απόλυσης, είναι ο μέσος όρος των βαθμολογιών που εξασφάλισε ο υποψήφιος στο συγκεκριμένο μάθημα στα δύο τετράμηνα των Παγκύπριων Εξετάσεων Απόλυσης.\n(β) για μάθημα που εξετάζεται ο υποψήφιος μόνο για σκοπούς Παγκύπριων Εξετάσεων Πρόσβασης και δεν εξετάστηκε προηγουμένως για σκοπούς Παγκύπριων Εξετάσεων Απόλυσης, αποφασίζεται από την αρμόδια αρχή."
    },
    {
      "provision_ref": "sec35",
      "section": "35",
      "title": "Άρθρο 35: Περίπτωση απρόοπτου φυσικού φαινομένου κατά τη διάρκεια των εξετάσεων",
      "content": "35.(1)Σε περίπτωση οποιουδήποτε απρόβλεπτου φυσικού ή άλλου φαινομένου, όπως σεισμός, πυρκαγιά κ.λπ., που θέτει σε κίνδυνο τη ζωή και την ασφάλεια των εξεταζομένων και όλων των εμπλεκομένων στις εξετάσεις, λαμβάνονται τα ενδεδειγμένα μέτρα και η αρμόδια αρχή εξετάζει κατά πόσον έχει επηρεαστεί το αδιάβλητο της εξεταστικής διαδικασίας που θα έχει ως συνέπεια την ακύρωση και επανάληψή της.\n(2) Σε περίπτωση που διαπιστωθεί οποιαδήποτε παραβίαση του αδιάβλητου των εξετάσεων η αρμόδια αρχή αποφασίζει για την εξέλιξη της εξεταστικής διαδικασίας."
    },
    {
      "provision_ref": "sec36",
      "section": "36",
      "title": "Άρθρο 36: Επιστροφή και φύλαξη γραπτών",
      "content": "36.-(1) Τα τετράδια απαντήσεων, μετά τη βαθμολόγησή τους, επιστρέφονται στην Υπηρεσία Εξετάσεων και φυλάσσονται υπό την ευθύνη της για δύο τουλάχιστον χρόνια, εκτός αν υπάρχει δικαστική υπόθεση σε εξέλιξη, οπότε τα συγκεκριμένα τετράδια απαντήσεων φυλάσσονται για όσο επιπρόσθετο χρόνο απαιτείται.\n(2) Με απόφαση της αρμόδιας αρχής, επιτρέπεται η χρήση και η μετακίνηση των γραπτών τετραδίων απαντήσεων των υποψηφίων, για τα οποία δεν υπάρχει καμιά δικαστική εκκρεμότητα είτε για ερευνητικούς σκοπούς είτε για περαιτέρω μελέτη των αποτελεσμάτων για εκπαιδευτικούς λόγους, τηρουμένων των διατάξεων του περί Επεξεργασίας Δεδομένων Προσωπικού Χαρακτήρα (Προστασία του Ατόμου) Νόμου."
    },
    {
      "provision_ref": "sec37",
      "section": "37",
      "title": "Άρθρο 37: Αδικήματα",
      "content": "37. Πρόσωπο το οποίο παραβιάζει οποιοδήποτε όρο της Υπεύθυνης Δήλωσης που έχει υπογράψει, σύμφωνα με το Παράρτημα ΙΙΙ, είναι ένοχο αδικήματος και, σε περίπτωση καταδίκης, υπόκειται σε φυλάκιση που δεν υπερβαίνει τα δύο χρόνια ή σε χρηματική ποινή που δεν υπερβαίνει τις δέκα χιλιάδες ευρώ (€10,000) ή και στις δύο αυτές ποινές."
    },
    {
      "provision_ref": "sec38",
      "section": "38",
      "title": "Άρθρο 38: Εξουσία έκδοσης διατάγματος από την αρμόδια αρχή",
      "content": "38.-(1) Η αρμόδια αρχή εξουσιοδοτείται όπως, το αργότερο μέχρι την 31η Ιανουαρίου εκάστου έτους, εκδίδει διάταγμα που περιλαμβάνει τον Οδηγό Παγκύπριων Εξετάσεων Πρόσβασης, για σκοπούς καλύτερης εφαρμογής των διατάξεων του παρόντος Νόμου:\nΝοείται ότι, η αρμόδια αρχή δύναται, σε περιπτώσεις ανωτέρας βίας που οφείλεται σε εχθροπραξίες, πόλεμο, τρομοκρατικές ενέργειες, πανδημία και φυσικές καταστροφές, να εκδίδει σε ημερομηνία μεταγενέστερη της 31 ης Ιανουαρίου εκάστου έτους και πριν από την ημερομηνία έναρξης των Παγκύπριων Εξετάσεων Πρόσβασης νέο διάταγμα αναθεωρώντας τον Οδηγό Παγκύπριων Εξετάσεων Πρόσβασης.\n(2) Η αρμόδια αρχή δύναται με διάταγμα που δημοσιεύεται στην Επίσημη Εφημερίδα της Δημοκρατίας να τροποποιεί τα Παραρτήματα Ι και ΙΙ του παρόντος Νόμου."
    },
    {
      "provision_ref": "sec39",
      "section": "39",
      "title": "Άρθρο 39: Έναρξη της ισχύος του παρόντος Νόμου",
      "content": "39.- (1) Ο παρών Νόμος τίθεται σε ισχύ από την 1 η Σεπτεμβρίου 2021.\n(2) Σε περίπτωση κατά την οποία διατάξεις του παρόντος Νόμου συγκρούονται με διατάξεις άλλων νόμων ή κανονισμών που ρυθμίζουν θέματα εισαγωγής στα Δημόσια ΑΑΕΙ της Κύπρου, υπερισχύουν οι διατάξεις του παρόντος Νόμου."
    },
    {
      "provision_ref": "sec40",
      "section": "40",
      "title": "Άρθρο 40: Κατάργηση και επιφυλάξεις",
      "content": "40.-(1) Από την ημερομηνία έναρξης της ισχύος του παρόντος Νόμου, οι περί Διεξαγωγής των Παγκύπριων Εξετάσεων Νόμοι του 2006 και 2007 καταργούνται.\n(2) Κανονισμοί και διατάγματα που εκδόθηκαν δυνάμει του Νόμου που αναφέρεται στο εδάφιο (1), εξακολουθούν να ισχύουν μέχρις ότου καταργηθούν ή αντικατασταθούν, στην έκταση που δεν αντίκεινται στις διατάξεις του παρόντος Νόμου."
    }
  ],
  "definitions": [
    {
      "term": "Αγωνόδικος Επιτροπή",
      "definition": "την Επιτροπή που ορίζεται για την αξιολόγηση των υποψηφίων στο εξεταζόμενο μάθημα της πρακτικής δοκιμασίας",
      "source_provision": "sec2"
    },
    {
      "term": "αναβαθμολογητής",
      "definition": "τον εκπαιδευτικό που είναι εντεταλμένος από την Υπηρεσία Εξετάσεων σε συνεργασία με τις Διευθύνσεις Μέσης Εκπαίδευσης για την επαναξιολόγηση των τετραδίων απαντήσεων των υποψηφίων κάθε μαθήματος του πλαισίου πρόσβασης",
      "source_provision": "sec2"
    },
    {
      "term": "αριθμός υποψηφίου",
      "definition": "το μοναδικό αριθμό που δίνεται από την Υπηρεσία Εξετάσεων στον υποψήφιο, για τους σκοπούς των Παγκύπριων Εξετάσεων Πρόσβασης, για τη συγκεκριμένη χρονιά που υποβάλλει αίτηση συμμετοχής και βρίσκεται στο δελτίο υποψηφίου",
      "source_provision": "sec2"
    },
    {
      "term": "αρμόδια αρχή",
      "definition": "τον Υπουργό Παιδείας και Πολιτισμού",
      "source_provision": "sec2"
    },
    {
      "term": "βαθμολογητής",
      "definition": "τον εκπαιδευτικό που ορίζεται από την Υπηρεσία Εξετάσεων σε συνεργασία με τις Διευθύνσεις Μέσης Εκπαίδευσης για τη βαθμολόγηση των τετραδίων απαντήσεων των υποψηφίων ή των άλλων μορφών αξιολόγησης, που περιλαμβάνονται στα πλαίσια πρόσβασης των Παγκύπριων Εξετάσεων Πρόσβασης",
      "source_provision": "sec2"
    },
    {
      "term": "δελτίο υποψηφίου",
      "definition": "την έντυπη ή την ηλεκτρονική επιστολή, η οποία αποστέλλεται από την Υπηρεσία Εξετάσεων προς τον υποψήφιο, με την οποία ενημερώνεται για τον αριθμό υποψηφίου και για τα εξεταστικά κέντρα στα οποία θα εξεταστεί",
      "source_provision": "sec2"
    },
    {
      "term": "δημόσιο σχολείο Μέσης Εκπαίδευσης",
      "definition": "που αποδίδεται στον όρο αυτό από το άρθρο 2 του περί Δημόσιας Εκπαιδευτικής Υπηρεσίας Νόμου",
      "source_provision": "sec2"
    },
    {
      "term": "δολίευση",
      "definition": "κάθε προσπάθεια που γίνεται από υποψήφιο για να ολοκληρώσει το εξεταστικό του δοκίμιο με δόλια μέσα, όπως η αντιγραφή από συνυποψήφιό του ή η κατοχή ή/και χρήση μη επιτρεπόμενων βοηθημάτων/σημειώσεων ή ηλεκτρονικών συσκευών στις οποίες αποθηκεύονται πληροφορίες και μεταφέρονται παράνομα στο εξεταστικό κέντρο ή η χρησιμοποίηση μέρους ή ολόκληρου του γραπτού άλλου υποψηφίου ως δικού του ή η αποδοχή ή/και παροχή βοήθειας από άλλους εξεταζομένους ή άλλο πρόσωπο ή η γνώση εκ των προτέρων των θεμάτων της εξέτασης ή η με οποιοδήποτε άλλο τρόπο απόπειρα εξαπάτησης με στόχο την επιτυχία στις εξετάσεις",
      "source_provision": "sec2"
    },
    {
      "term": "Ειδική Επιτροπή Παροχής Διευκολύνσεων",
      "definition": "την Ειδική Επιτροπή που ορίζεται από την αρμόδια αρχή, σύμφωνα με τις διατάξεις του άρθρου 11, για την εξέταση των αιτήσεων των υποψηφίων με ειδικές ανάγκες και την παροχή των αναγκαίων διευκολύνσεων κατά τη διεξαγωγή των Παγκύπριων Εξετάσεων Πρόσβασης",
      "source_provision": "sec2"
    },
    {
      "term": "εξεταστικό κέντρο",
      "definition": "το κέντρο που ορίζεται από την Υπηρεσία Εξετάσεων, σε συνεργασία με τις Διευθύνσεις Μέσης Εκπαίδευσης του Υπουργείου Παιδείας και Πολιτισμού, για τη διεξαγωγή των Παγκύπριων Εξετάσεων Πρόσβασης",
      "source_provision": "sec2"
    },
    {
      "term": "επιτηρητής",
      "definition": "τον εκπαιδευτικό που είναι εντεταλμένος για την επιτήρηση της ομαλής και αδιάβλητης διεξαγωγής των Παγκύπριων Εξετάσεων Πρόσβασης",
      "source_provision": "sec2"
    },
    {
      "term": "Επιτροπή Εξεταστικού Κέντρου",
      "definition": "την επιτροπή που ορίζεται από τη διεύθυνση του σχολείου που λειτουργεί ως εξεταστικό κέντρο, η οποία αναλαμβάνει τη διεκπεραίωση όλων των απαραίτητων διαδικασιών που σχετίζονται με τη διενέργεια και ολοκλήρωση των Παγκύπριων Εξετάσεων Πρόσβασης στα εξεταστικά κέντρα, συμπεριλαμβανομένης της διαδικασίας παραλαβής των εξεταστικών δοκιμίων από το συντονιστικό κέντρο της επαρχίας και της παράδοσης των τετραδίων απαντήσεων των υποψηφίων στο συντονιστικό κέντρο της επαρχίας στην οποία ανήκει το κέντρο",
      "source_provision": "sec2"
    },
    {
      "term": "Επιτροπή Θεματοθέτησης",
      "definition": "την πενταμελή επιτροπή θεματοθετών που έχει ως όρους εντολής την ετοιμασία θεμάτων για κάθε μέρος του εξεταστικού δοκιμίου, όπως και την κατάρτιση του εξεταστικού δοκιμίου, σύμφωνα με τις οδηγίες της αρμόδιας αρχής, τα οποία υποβάλλουν για έλεγχο στην Επιτροπή Ελέγχου",
      "source_provision": "sec2"
    },
    {
      "term": "ΕΠΕΠ",
      "definition": "την επιτροπή, η οποία έχει την ευθύνη της τελικής επιλογής των θεματοθετών, καθώς και την ευθύνη της επιλογής των βαθμολογητών των Παγκύπριων Εξετάσεων Πρόσβασης",
      "source_provision": "sec2"
    },
    {
      "term": "θεματοθέτης",
      "definition": "τον εκπαιδευτικό που διορίζεται ως μέλος της Επιτροπής Θεματοθέτησης και έχει την ευθύνη μαζί με τα υπόλοιπα μέλη της επιτροπής για την ετοιμασία εξεταστικού δοκιμίου συγκεκριμένου μαθήματος που περιλαμβάνεται στα πλαίσια πρόσβασης",
      "source_provision": "sec2"
    },
    {
      "term": "θέση",
      "definition": "τη διαθέσιμη θέση στα ΑΑΕΙ της Κύπρου, την οποία διεκδικούν οι υποψήφιοι των Παγκύπριων Εξετάσεων Πρόσβασης",
      "source_provision": "sec2"
    },
    {
      "term": "ιδιωτικό σχολείο Μέσης Εκπαίδευσης",
      "definition": "που αποδίδεται στον όρο αυτό από τον περί Ιδιωτικών Σχολείων και Φροντιστηρίων Νόμο",
      "source_provision": "sec2"
    },
    {
      "term": "κέντρο βαθμολόγησης",
      "definition": "το κέντρο, το οποίο ορίζεται από την Υπηρεσία Εξετάσεων για τη διεκπεραίωση της διαδικασίας βαθμολόγησης των τετραδίων απαντήσεων των υποψηφίων",
      "source_provision": "sec2"
    },
    {
      "term": "λυκειακός κύκλος",
      "definition": "που αποδίδεται στον όρο αυτό από τους περί Λειτουργίας των Δημόσιων Σχολείων Μέσης Εκπαίδευσης Κανονισμούς",
      "source_provision": "sec2"
    },
    {
      "term": "μέλος Επιτροπής Εξεταστικού Κέντρου",
      "definition": "τον εκπαιδευτικό που ορίζεται από τη Διεύθυνση του Σχολείου Μέσης Εκπαίδευσης που λειτουργεί ως εξεταστικό κέντρο, σύμφωνα με τους κανόνες και τις οδηγίες της Υπηρεσίας Εξετάσεων",
      "source_provision": "sec2"
    },
    {
      "term": "οδηγός διόρθωσης",
      "definition": "τις γραπτές οδηγίες που δίνονται από τους θεματοθέτες προς τους βαθμολογητές, οι οποίες δύναται να διαμορφώνονται μετά το συντονισμό βαθμολόγησης και αφορούν τον τρόπο βαθμολόγησης των γραπτών απαντήσεων",
      "source_provision": "sec2"
    },
    {
      "term": "Οδηγός Παγκύπριων Εξετάσεων Πρόσβασης",
      "definition": "το έντυπο ή το ηλεκτρονικό αρχείο που εκδίδει ή αναρτά στην ιστοσελίδα της η Υπηρεσία Εξετάσεων, σύμφωνα με τις διατάξεις του άρθρου 30, κατόπιν έγκρισης της αρμόδιας αρχής",
      "source_provision": "sec2"
    },
    {
      "term": "πίνακας προδιαγραφών",
      "definition": "τον πίνακα που περιέχει τις παραμέτρους και προδιαγραφές, βάσει των οποίων καταρτίζεται το εξεταστικό δοκίμιο κάθε εξεταζόμενου μαθήματος",
      "source_provision": "sec2"
    },
    {
      "term": "πιστοποιητικό πρόσβασης",
      "definition": "τη βεβαίωση που χορηγεί σε κάθε ενδιαφερόμενο υποψήφιο η Υπηρεσία Εξετάσεων, στην οποία αναγράφεται το Τμήμα/Σχολή επιτυχίας του υποψηφίου στα Δημόσια ΑΑΕΙ της Κύπρου, σε περίπτωση που έχει επιτύχει και επιθυμεί πρόσβαση στα ΑΑΕΙ της Κύπρου, καθώς και οι αρχικές βαθμολογίες που εξασφάλισε ο υποψήφιος, όπως και οι βαθμοί κατάταξης ανά πλαίσιο πρόσβασης",
      "source_provision": "sec2"
    },
    {
      "term": "πλαίσιο πρόσβασης",
      "definition": "την ομάδα μαθημάτων που ορίζεται από την αρμόδια αρχή ανά Τμήμα/Σχολή Τριτοβάθμιας Εκπαίδευσης, τα οποία αποτελούν τα εξεταζόμενα μαθήματα στις Παγκύπριες Εξετάσεις Πρόσβασης, για σκοπούς εισαγωγής στα Δημόσια ΑΑΕΙ της Κύπρου",
      "source_provision": "sec2"
    },
    {
      "term": "πρακτική δοκιμασία",
      "definition": "το εξεταζόμενο μάθημα πρόσβασης κατά το οποίο ο υποψήφιος εξετάζεται σε αθλητικές δοκιμασίες, όπως καθορίζονται στο Παράρτημα Ι, οι οποίες βαθμολογούνται από την οριζόμενη Αγωνόδικο Επιτροπή",
      "source_provision": "sec2"
    },
    {
      "term": "πρόεδρος Επιτροπής Εξεταστικού Κέντρου",
      "definition": "τον εκπαιδευτικό που ορίζεται από τη διεύθυνση του σχολείου Μέσης Εκπαίδευσης που λειτουργεί ως εξεταστικό κέντρο και έχει τη γενική ευθύνη της ομαλής λειτουργίας του συγκεκριμένου εξεταστικού κέντρου κατά τη διεξαγωγή των Παγκύπριων Εξετάσεων Πρόσβασης, σύμφωνα με τους κανόνες και τις οδηγίες της Υπηρεσίας Εξετάσεων",
      "source_provision": "sec2"
    },
    {
      "term": "Υπεύθυνη Δήλωση",
      "definition": "τη δήλωση, το περιεχόμενο της οποίας καθορίζεται στο Παράρτημα ΙΙΙ",
      "source_provision": "sec2"
    },
    {
      "term": "Υπηρεσία Εξετάσεων",
      "definition": "την υπηρεσία του Υπουργείου Παιδείας και Πολιτισμού, η οποία έχει την ευθύνη για την προετοιμασία, διεξαγωγή και εξαγωγή των αποτελεσμάτων των Παγκύπριων Εξετάσεων Πρόσβασης",
      "source_provision": "sec2"
    },
    {
      "term": "υποψήφιος",
      "definition": "το πρόσωπο που συμμετέχει στις Παγκύπριες Εξετάσεις Πρόσβασης, για σκοπούς εξασφάλισης του πιστοποιητικού πρόσβασης και του βαθμού κατάταξης, καθώς και στη διαδικασία της κατανομής των θέσεων στα Δημόσια ΑΑΕΙ της Κύπρου ή/και της Ελλάδας",
      "source_provision": "sec2"
    },
    {
      "term": "υποψήφιος με ειδικές ανάγκες",
      "definition": "τον υποψήφιο που σύμφωνα με τις διατάξεις του περί Αγωγής και Εκπαίδευσης Παιδιών με Ειδικές Ανάγκες Νόμου, έχει σοβαρή μαθησιακή ή ειδική μαθησιακή, λειτουργική και προσαρμοστική, δυσκολία που οφείλεται σε σωματικές, συμπεριλαμβανομένων των αισθητηριακών, διανοητικές ή άλλες γνωστικές ή ψυχικές ανεπάρκειες ή άλλου είδους εκ γενετής ή επίκτητες δυσχέρειες που χρήζουν ειδικής/ων διευκόλυνσης/σεων, για σκοπούς συμμετοχής στις Παγκύπριες Εξετάσεις Πρόσβασης",
      "source_provision": "sec2"
    }
  ]
}
